[
	{"name": "Kamura Glaive I", "rank": "Low", "raw": 50, "affinity": 0, "defense": 0, "rarity": 1, "slots": [], "kinsect_level": 1, "element": null, "rampage_skills": ["Attack Boost I", "Affinity Boost II", "Defense Boost I"], "crafting_list": {"Zenny": 300, "Points": "Ore x3 Points"}},
	{"name": "Kamura Glaive II", "rank": "Low", "raw": 60, "affinity": 0, "defense": 0, "rarity": 1, "slots": [], "kinsect_level": 1, "element": null, "rampage_skills": ["Attack Boost I", "Affinity Boost II", "Defense Boost I"], "crafting_list": {"Zenny": 200, "Iron Ore": 1}},
	{"name": "Kamura Glaive III", "rank": "Low", "raw": 90, "affinity": 0, "defense": 0, "rarity": 2, "slots": [], "kinsect_level": 2, "element": null, "rampage_skills": ["Attack Boost I", "Affinity Boost II", "Defense Boost II"], "crafting_list": {"Zenny": 1000, "Points": "Neopteron x5 Points", "Machalite Ore": 3, "Rhenoplos Shell": 2}},
	{"name": "Kamura Glaive IV", "rank": "Low", "raw": 140, "affinity": 0, "defense": 0, "rarity": 3, "slots": [], "kinsect_level": 3, "element": null, "rampage_skills": ["Attack Boost II", "Affinity Boost II", "Defense Boost II"], "crafting_list": {"Zenny": 5000, "Points": "Monster x10 Points", "Almudron Claw": 1, "Firestone": 3}},
	{"name": "Kamura Glaive V", "rank": "High", "raw": 150, "affinity": 0, "defense": 0, "rarity": 4, "slots": [2], "kinsect_level": 4, "element": null, "rampage_skills": ["Affinity Boost III", "Defense Boost II", "Master Rider"], "crafting_list": {"Zenny": 5000, "Points": "Monster x10 Points", "Almudron Claw": 1, "Firestone": 3}},
	{"name": "Kamura Ninja Glaive", "rank": "High", "raw": 190, "affinity": 0, "defense": 0, "rarity": 5, "slots": [2, 1], "kinsect_level": 6, "element": null, "rampage_skills": ["Affinity Boost IV", "Defense Boost II", "Master Rider"], "crafting_list": {"Zenny": 20000, "Points": "Bone+ x15 Points", "Firecell Stone": 2, "Jyuratodus Carapace": 2, "Wyvern Gem": 1}},
	{"name": "Hidden Scythe I", "rank": "Low", "raw": 100, "affinity": 40, "defense": 0, "rarity": 3, "slots": [], "kinsect_level": 2, "element": null, "rampage_skills": ["Attack Boost II", "Affinity Boost I", "Master Rider"], "crafting_list": {"Zenny": 4200, "Nargacuga Cutwing": 2, "Nargacuga Scale": 3, "Dragonite Ore": 3}},
	{"name": "Hidden Scythe II", "rank": "High", "raw": 170, "affinity": 40, "defense": 0, "rarity": 5, "slots": [2], "kinsect_level": 5, "element": null, "rampage_skills": ["Attack Boost III", "Affinity Boost I", "Master Rider"], "crafting_list": {"Zenny": 28000, "Narga Razor": 2, "Nargacuga Scale +": 5, "Nargacuga Marrow": 2}},
	{"name": "Evening Calm", "rank": "High", "raw": 190, "affinity": 40, "defense": 0, "rarity": 6, "slots": [2], "kinsect_level": 7, "element": null, "rampage_skills": ["Attack Boost III", "Affinity Boost II", "Master Rider"], "crafting_list": {"Zenny": 42000, "Points": "Nargacuga+ x15 Points", "Rakna-Kadaki Sharpclaw": 2, "Narga Medulla": 1}},
	{"name": "Fox Halberd I", "rank": "Low", "raw": 120, "affinity": 10, "defense": 0, "rarity": 3, "slots": [], "kinsect_level": 2, "element": ["Water", 12], "rampage_skills": ["Attack Boost II", "Affinity I", "Water Boost I"], "crafting_list": {"Zenny": 4200, "Mizutsune Claw": 2, "Mizutsune Scale": 3, "Bubblefoam": 3}},
	{"name": "Fox Halberd II", "rank": "High", "raw": 170, "affinity": 10, "defense": 0, "rarity": 5, "slots": [1], "kinsect_level": 5, "element": ["Water", 16], "rampage_skills": ["Attack Boost II", "Affinity II", "Water Boost II"], "crafting_list": {"Zenny": 28000, "Mizutsune Claw +": 2, "Mizutsune Scale +": 4, "Bubblefoam": 3, "Mizutsune Plate": 1}},
	{"name": "Frilled Jab I", "rank": "Low", "raw": 110, "affinity": 0, "defense": 0, "rarity": 2, "slots": [], "kinsect_level": 2, "element": ["Sleep", 10], "rampage_skills": ["Attack Boost I", "Sleep Boost I", "Dulling Strike"], "crafting_list": {"Zenny": 3900, "Somnacanth Talon": 3, "Somnacanth Shell": 2, "Somnacanth Dust": 2, "Monster Fluid": 1}},
	{"name": "Frilled Jab II", "rank": "Low", "raw": 120, "affinity": 0, "defense": 0, "rarity": 3, "slots": [], "kinsect_level": 3, "element": ["Sleep", 12], "rampage_skills": ["Attack Boost I", "Sleep Boost I", "Dulling Strike"], "crafting_list": {"Zenny": 3900, "Points": "Somnacanth x8 Points", "Mizutsune Claw": 3, "Somnacanth Fin": 2}},
	{"name": "Illusory Frilled Jab", "rank": "High", "raw": 190, "affinity": 0, "defense": 0, "rarity": 5, "slots": [1, 1], "kinsect_level": 6, "element": ["Sleep", 15], "rampage_skills": ["Attack Boost III", "Sleep Boost I", "Dulling Strike"], "crafting_list": {"Zenny": 26000, "Somnacanth Talon +": 4, "Somnacanth Shell +": 3, "Somnacanth Sedative": 2, "Wyvern Gem": 1}},
	{"name": "Tigrex Kaina I", "rank": "Low", "raw": 160, "affinity": -15, "defense": 0, "rarity": 3, "slots": [], "kinsect_level": 2, "element": null, "rampage_skills": ["Attack Boost II", "Affinity Boost I", "Brutal Strike"], "crafting_list": {"Zenny": 7000, "Tigrex Claw": 3, "Tigrex Shell": 3, "Tigrex Tail": 1}},
	{"name": "Tigrex Kaina II", "rank": "High", "raw": 210, "affinity": -15, "defense": 0, "rarity": 6, "slots": [], "kinsect_level": 5, "element": null, "rampage_skills": ["Attack Boost II", "Affinity Boost II", "Brutal Strike"], "crafting_list": {"Zenny": 42000, "Tigrex Claw +": 3, "Tigrex Carapace": 4, "Tigrex Scalp": 1}},
	{"name": "Tigerclaw Glaive", "rank": "High", "raw": 220, "affinity": -10, "defense": 0, "rarity": 6, "slots": [1], "kinsect_level": 6, "element": null, "rampage_skills": ["Attack Boost III", "Affinity Boost II", "Brutal Strike"], "crafting_list": {"Zenny": 56000, "Teostra Claw +": 3, "Tigrex Maw": 1, "Points": "Tigrex x15"}},
	{"name": "Leaping Glaive I", "rank": "Low", "raw": 100, "affinity": 0, "defense": 10, "rarity": 2, "slots": [], "kinsect_level": 2, "element": ["Water", 10], "rampage_skills": ["Defense Boost I", "Water Boost I", "Dulling Strike"], "crafting_list": {"Zenny": 1800, "Tetranadon Beak": 2, "Tetra Carapace": 3, "Aqua Sac": 2, "Machalite Ore": 3}},
	{"name": "Leaping Glaive II", "rank": "High", "raw": 160, "affinity": 0, "defense": 20, "rarity": 4, "slots": [], "kinsect_level": 4, "element": ["Water", 12], "rampage_skills": ["Defense Boost I", "Water Boost II", "Dulling Strike"], "crafting_list": {"Zenny": 9600, "Tetranadon Beak +": 2, "Tetra Carapace +": 3, "Torrent Sac": 2, "Carbalite Ore": 3}},
	{"name": "Leapfrog", "rank": "High", "raw": 210, "affinity": 0, "defense": 20, "rarity": 6, "slots": [], "kinsect_level": 7, "element": ["Water", 14], "rampage_skills": ["Defense Boost I", "Water Boost III", "Dulling Strike"], "crafting_list": {"Zenny": 36000, "Points": "Tetranadon+ x10 Points", "Golden Sludge": 3, "Tetranadon Disc +": 2}},
	{"name": "Iron Blade I", "rank": "Low", "raw": 80, "affinity": 0, "defense": 0, "rarity": 1, "slots": [], "kinsect_level": 1, "element": null, "rampage_skills": ["Attack Boost I", "Affinity Boost I", "Defense Boost II"], "crafting_list": {"Zenny": 300, "Iron Ore": 3}},
	{"name": "Iron Blade II", "rank": "Low", "raw": 100, "affinity": 0, "defense": 0, "rarity": 1, "slots": [], "kinsect_level": 1, "element": null, "rampage_skills": ["Attack Boost I", "Affinity Boost I", "Defense Boost II"], "crafting_list": {"Zenny": 600, "Icium": 2, "Earth Crystal": 2}},
	{"name": "Steel Blade", "rank": "Low", "raw": 120, "affinity": 0, "defense": 0, "rarity": 2, "slots": [], "kinsect_level": 2, "element": null, "rampage_skills": ["Attack Boost II", "Affinity Boost I", "Defense Boost II"], "crafting_list": {"Zenny": 2000, "Points": "Ore x8 Points", "Dragonite Ore": 3}},
	{"name": "Iron Bayonet I", "rank": "Low", "raw": 140, "affinity": 0, "defense": 0, "rarity": 3, "slots": [], "kinsect_level": 2, "element": null, "rampage_skills": ["Attack Boost II", "Defense Boost II", "Silkbind Boost"], "crafting_list": {"Zenny": 3000, "Monster Bone +": 2, "Firestone": 1}},
	{"name": "Iron Bayonet II", "rank": "High", "raw": 170, "affinity": 0, "defense": 0, "rarity": 4, "slots": [1], "kinsect_level": 3, "element": null, "rampage_skills": ["Attack Boost II", "Defense Boost III", "Silkbind Boost"], "crafting_list": {"Zenny": 8000, "Carbalite Ore": 2, "Gracium": 2, "Monster Broth": 3}},
	{"name": "Hiten Blade", "rank": "High", "raw": 210, "affinity": 0, "defense": 0, "rarity": 5, "slots": [1], "kinsect_level": 5, "element": null, "rampage_skills": ["Attack Boost III", "Defense Boost III", "Silkbind Boost"], "crafting_list": {"Zenny": 8000, "Points": "Ore+ x12 Points", "Firecell Stone": 3, "Fucium Ore": 3}},
	{"name": "Rathmaul I", "rank": "High", "raw": 180, "affinity": 0, "defense": 0, "rarity": 5, "slots": [1], "kinsect_level": 4, "element": ["Fire", 25], "rampage_skills": ["Attack Boost II", "Fire Boost I", "Element Exploit"], "crafting_list": {"Zenny": 42000, "Rathalos Scale +": 4, "Rathalos Carapace": 4, "Rathalos Wing": 2, "Rathalos Marrow": 1}},
	{"name": "Rathmaul II", "rank": "High", "raw": 180, "affinity": 0, "defense": 0, "rarity": 6, "slots": [1], "kinsect_level": 6, "element": ["Fire", 27], "rampage_skills": ["Attack Boost II", "Fire Boost I", "Element Exploit"], "crafting_list": {"Zenny": 42000, "Rakna-Kadaki Glowgut": 2, "Rath Wingtalon +": 2, "Rathalos Plate": 1}},
	{"name": "Firedance Rathmaul", "rank": "High", "raw": 190, "affinity": 0, "defense": 0, "rarity": 6, "slots": [1], "kinsect_level": 7, "element": ["Fire", 30], "rampage_skills": ["Attack Boost III", "Fire Boost I", "Element Exploit"], "crafting_list": {"Zenny": 56000, "Teostra Webbing": 2, "Rathalos Ruby": 1, "Points": "Rathalos+ x12 Points"}},
	{"name": "Bolt Chamber I", "rank": "High", "raw": 150, "affinity": 0, "defense": 0, "rarity": 4, "slots": [2], "kinsect_level": 3, "element": ["Thunder", 25], "rampage_skills": ["Attack Boost II", "Thunder Boost I", "Thunderblight Exploit"], "crafting_list": {"Zenny": 15600, "Pearl Hide": 3, "Pale Bone": 2, "Thunder Sac": 3, "Carbalite Ore": 4}},
	{"name": "Bolt Chamber II", "rank": "High", "raw": 160, "affinity": 0, "defense": 0, "rarity": 5, "slots": [2], "kinsect_level": 4, "element": ["Thunder", 29], "rampage_skills": ["Attack Boost III", "Thunder Boost I", "Thunderblight Exploit"], "crafting_list": {"Zenny": 15600, "Points": "Khezu+ x8 Points", "Novacrystal": 2, "Suspicious Fang +": 2}},
	{"name": "Full Bolt Chamber", "rank": "High", "raw": 180, "affinity": 0, "defense": 0, "rarity": 6, "slots": [2], "kinsect_level": 6, "element": ["Thunder", 33], "rampage_skills": ["Attack Boost IV", "Thunder Boost II", "Thunderblight Exploit"], "crafting_list": {"Zenny": 39000, "Bazelgeuse Scale +": 2, "Pale Steak": 2, "Tobi-Kadachi Electrode +": 2, "Wyvern Gem": 1}},
	{"name": "Princess Regalia I", "rank": "Low", "raw": 110, "affinity": 0, "defense": 0, "rarity": 2, "slots": [], "kinsect_level": 2, "element": ["Poison", 19], "rampage_skills": ["Attack Boost I", "Poison Boost I", "Small Monster Exploit"], "crafting_list": {"Zenny": 3900, "Rathian Spike": 2, "Rathian Shell": 3, "Rath Wingtalon": 2, "Lightcrystal": 2}},
	{"name": "Princess Regalia II", "rank": "High", "raw": 180, "affinity": 0, "defense": 0, "rarity": 5, "slots": [], "kinsect_level": 5, "element": ["Poison", 23], "rampage_skills": ["Attack Boost II", "Poison Boost I", null], "crafting_list": {"Zenny": 15600, "Rathian Spike +": 3, "Rathian Carapace": 33, "Novacrystal": 1, "Rathian Plate": 1}},
	{"name": "Queen Regalia", "rank": "High", "raw": 210, "affinity": 0, "defense": 0, "rarity": 6, "slots": [], "kinsect_level": 6, "element": ["Poison", 25], "rampage_skills": ["Attack Boost II", "Poison Boost I", "Small Monster Exploit"], "crafting_list": {"Zenny": 26000, "Points": "Rathian+ x12 points", "Rathalos Carapace": 2, "Rathian Ruby": 1}},
	{"name": "Aknosom Pike I", "rank": "Low", "raw": 100, "affinity": 0, "defense": 0, "rarity": 2, "slots": [], "kinsect_level": 2, "element": ["Fire", 12], "rampage_skills": ["Attack Boost I", "Fire Boost I", "Fireblight Exploit"], "crafting_list": {"Zenny": 1800, "Aknosom Crest": 1, "Aknosom Feather": 3, "Machalite Ore": 3, "Flame Sac": 1}},
	{"name": "Aknosom Pike II", "rank": "Low", "raw": 110, "affinity": 0, "defense": 0, "rarity": 2, "slots": [], "kinsect_level": 3, "element": ["Fire", 15], "rampage_skills": ["Attack Boost II", "Fire Boost I", "Fireblight Exploit"], "crafting_list": {"Zenny": 2400, "Aknosom": 0, "Firestone": 2, "Aknosom Beak": 1}},
	{"name": "Daybreak Glaive", "rank": "High", "raw": 150, "affinity": 0, "defense": 0, "rarity": 4, "slots": [2], "kinsect_level": 4, "element": ["Fire", 22], "rampage_skills": ["Attack Boost II", "Fire Boost II", "Fireblight Exploit"], "crafting_list": {"Zenny": 12000, "Aknosom Crest +": 2, "Aknosom Feather +": 4, "Carbalite Ore": 3, "Bird Wyvern Gem": 1}},
	{"name": "Kulu Glaive I", "rank": "Low", "raw": 100, "affinity": 10, "defense": 0, "rarity": 2, "slots": [], "kinsect_level": 3, "element": null, "rampage_skills": ["Affinity Boost II", "Kinsect Level Boost", "Spiribird Doubled"], "crafting_list": {"Zenny": 1200, "Kulu-Ya-Ku Scale": 3, "Kulu-Ya-Ku Beak": 1, "Machalite Ore": 3}},
	{"name": "Kulu Glaive II", "rank": "Low", "raw": 140, "affinity": 10, "defense": 0, "rarity": 3, "slots": [], "kinsect_level": 3, "element": null, "rampage_skills": ["Affinity Boost II", "Kinsect Level Boost", "Spiribird Doubled"], "crafting_list": {"Zenny": 3600, "Points": "Kulu-Ya-Ku x8 Points", "Monster Bone +": 2, "Kulu-Ya-Ku Plume": 1}},
	{"name": "Kulu Pike", "rank": "High", "raw": 150, "affinity": 10, "defense": 0, "rarity": 4, "slots": [1, 1, 1], "kinsect_level": 4, "element": null, "rampage_skills": ["Affinity Boost III", "Kinsect Level Boost", "Spiribird Doubled"], "crafting_list": {"Zenny": 12000, "Kulu-Ya-Ku Scale +": 4, "Kulu-Ya-Ku Hide +": 2, "Kulu-Ya-Ku Beak +": 2, "Bird Wyvern Gem": 1}},
	{"name": "Kadachi Glaive I", "rank": "Low", "raw": 100, "affinity": 10, "defense": 0, "rarity": 2, "slots": [], "kinsect_level": 3, "element": ["Thunder", 12], "rampage_skills": ["Attack Boost I", "Affinity Boost I", "Thunder Boost II"], "crafting_list": {"Zenny": 2600, "Tobi-Kadachi Pelt": 3, "Tobi-Kadachi Claw": 1, "Dragonite Ore": 3}},
	{"name": "Kadachi Glaive II", "rank": "Low", "raw": 140, "affinity": 10, "defense": 0, "rarity": 3, "slots": [], "kinsect_level": 3, "element": ["Thunder", 15], "rampage_skills": ["Attack Boost I", "Affinity Boost II", "Thunder Boost II"], "crafting_list": {"Zenny": 6500, "Points": "Tobi-Kadachi x10 Points", "Massive Bone": 2, "Tobi-Kadachi Electrode": 2}},
	{"name": "Shocking Pike", "rank": "High", "raw": 170, "affinity": 10, "defense": 0, "rarity": 5, "slots": [1], "kinsect_level": 6, "element": ["Thunder", 22], "rampage_skills": ["Attack Boost II", "Affinity Boost II", "Thunder Boost III"], "crafting_list": {"Zenny": 26000, "Tobi-Kadachi Pelt +": 4, "Tobi-Kadachi Claw +": 2, "Tobi-Kadachi Electrode +": 2, "Wyvern Gem": 1}},
	{"name": "Lagombaglaive I", "rank": "Low", "raw": 80, "affinity": 0, "defense": 0, "rarity": 1, "slots": [], "kinsect_level": 2, "element": ["Ice", 15], "rampage_skills": ["Attack Boost I", "Ice Boost II", "Small Monster Exploit"], "crafting_list": {"Zenny": 1080, "Lagombi Ear": 1, "Lagombi Pelt": 3, "Lagombi Plastron": 2, "Icium": 2}},
	{"name": "Lagombaglaive II", "rank": "High", "raw": 150, "affinity": 0, "defense": 0, "rarity": 4, "slots": [1, 1], "kinsect_level": 4, "element": ["Ice", 23], "rampage_skills": ["Attack Boost I", "Ice Boost II", "Dulling Strike"], "crafting_list": {"Zenny": 1080, "Lagombi Plastron +": 2, "Lagombi Pelt +": 3, "Gracium": 1}},
	{"name": "Lagombavarice", "rank": "High", "raw": 170, "affinity": 0, "defense": 0, "rarity": 5, "slots": [1, 1], "kinsect_level": 5, "element": ["Ice", 26], "rampage_skills": ["Attack Boost II", "Ice Boost II", "Dulling Strike"], "crafting_list": {"Zenny": 18000, "Fucium Ore": 2, "Lagombi Ear +": 2, "Beast Gem": 1}},
	{"name": "Bone Staff I", "rank": "Low", "raw": 90, "affinity": 0, "defense": 0, "rarity": 1, "slots": [], "kinsect_level": 2, "element": null, "rampage_skills": ["Attack Boost II", "Affinity Boost I", "Defense Boost I"], "crafting_list": {"Zenny": 300, "Monster Bone S": 3}},
	{"name": "Bone Staff II", "rank": "Low", "raw": 110, "affinity": 0, "defense": 0, "rarity": 1, "slots": [], "kinsect_level": 2, "element": null, "rampage_skills": ["Attack Boost II", "Affinity Boost I", "Defense Boost I"], "crafting_list": {"Zenny": 600, "Dragonhusk Shard": 4, "Twisted Remains": 2}},
	{"name": "Aerial Glaive", "rank": "Low", "raw": 120, "affinity": 0, "defense": 0, "rarity": 2, "slots": [], "kinsect_level": 3, "element": null, "rampage_skills": ["Attack Boost II", "Affinity Boost II", "Defense Boost I"], "crafting_list": {"Zenny": 1000, "Eroded Skeleton": 3, "Monster Bone M": 2, "Jumbo Bone": 2}},
	{"name": "Sturdy Glaive I", "rank": "Low", "raw": 150, "affinity": 0, "defense": 0, "rarity": 3, "slots": [], "kinsect_level": 4, "element": null, "rampage_skills": ["Attack Boost II", "Affinity Boost II", "Dulling Strike"], "crafting_list": {"Zenny": 3000, "Monster Bone +": 2, "Rathalos Scale": 2, "Monster Fluid": 3}},
	{"name": "Sturdy Glaive II", "rank": "High", "raw": 180, "affinity": 0, "defense": 0, "rarity": 4, "slots": [], "kinsect_level": 5, "element": null, "rampage_skills": ["Attack Boost III", "Affinity Boost II", "Dulling Strike"], "crafting_list": {"Zenny": 8000, "Points": "Bone+ x8 Points", "Twisted Rockbone": 4, "Monster Broth": 3}},
	{"name": "Sturdy Glaive Redux", "rank": "High", "raw": 220, "affinity": 0, "defense": 0, "rarity": 5, "slots": [], "kinsect_level": 7, "element": null, "rampage_skills": ["Attack Boost IV", "Affinity Boost II", "Dulling Strike"], "crafting_list": {"Zenny": 20000, "Points": "Bone+ x10 Points", "Monster Hardbone": 3, "Uroktor scale +": 3, "Rathalos Scale +": 3}},
	{"name": "Sky-High Glaive I", "rank": "High", "raw": 130, "affinity": 0, "defense": 0, "rarity": 4, "slots": [2], "kinsect_level": 4, "element": ["Paralysis", 20], "rampage_skills": ["Attack Boost III", "Silkbind Boost", "Anti-Aerial Species"], "crafting_list": {"Zenny": 12000, "Monster Keenbone": 4, "Jagras Hide +": 4, "Paralysis Sac": 3}},
	{"name": "Sky-High Glaive II", "rank": "High", "raw": 150, "affinity": 0, "defense": 0, "rarity": 5, "slots": [3], "kinsect_level": 5, "element": ["Paralysis", 22], "rampage_skills": ["Attack Boost III", "Silkbind Boost", "Anti-Aerial Species"], "crafting_list": {"Zenny": 12000, "Points": "Small Monster+ x8 Points", "Omniplegia Sac": 2, "Rhenoplos Carapace": 2}},
	{"name": "Highest of Glaives", "rank": "High", "raw": 170, "affinity": 0, "defense": 0, "rarity": 6, "slots": [3], "kinsect_level": 7, "element": ["Paralysis", 25], "rampage_skills": ["Attack Boost IV", "Silkbind Boost", "Anti-Aerial Species"], "crafting_list": {"Zenny": 30000, "Tigrex Fang +": 2, "Firecell Stone": 2, "Great Stoutbone": 4}},
	{"name": "Diablos Rod I", "rank": "High", "raw": 200, "affinity": -10, "defense": 0, "rarity": 6, "slots": [], "kinsect_level": 4, "element": null, "rampage_skills": ["Attack Boost II", "Defense Boost I", "Kinsect Level Boost"], "crafting_list": {"Zenny": 54000, "Diablos Ridge +": 4, "Diablos Tailcase": 2, "Diablos Carapace": 3, "Monster Hardbone": 3}},
	{"name": "Diablos Rod II", "rank": "High", "raw": 210, "affinity": -10, "defense": 0, "rarity": 6, "slots": [], "kinsect_level": 5, "element": null, "rampage_skills": ["Attack Boost II", "Defense Boost II", "Kinsect Level Boost"], "crafting_list": {"Zenny": 56000, "Elder Dragon Bone": 3, "Majestic Horn": 2, "Diablos Marrow": 2}},
	{"name": "Flammenkaefer I", "rank": "Low", "raw": 140, "affinity": -15, "defense": 0, "rarity": 3, "slots": [], "kinsect_level": 2, "element": ["Fire", 12], "rampage_skills": ["Affinity Boost I", "Fire Boost I", "Brutal Strike"], "crafting_list": {"Zenny": 6300, "Anjanath Fang": 4, "Anjanath Pelt": 2, "Anjanath Scale": 2, "Flame Sac": 1}},
	{"name": "Flammenkaefer II", "rank": "High", "raw": 210, "affinity": -15, "defense": 0, "rarity": 5, "slots": [2, 1], "kinsect_level": 6, "element": ["Fire", 15], "rampage_skills": ["Affinity Boost I", "Fire Boost II", "Brutal Strike"], "crafting_list": {"Zenny": 28000, "Anjanath Fang +": 4, "Anjanath Pelt +": 3, "Monster Hardbone": 3}},
	{"name": "Gnashing Flammenkaefer", "rank": "High", "raw": 220, "affinity": -15, "defense": 0, "rarity": 6, "slots": [2, 1], "kinsect_level": 7, "element": ["Fire", 18], "rampage_skills": ["Affinity Boost II", "Fire Boost III", "Brutal Strike"], "crafting_list": {"Zenny": 42000, "Points": "Anjanath+ x10 Points", "Tigrex Fang +": 3, "Anjanath Gem": 1}},
	{"name": "Gossglaive I", "rank": "Low", "raw": 160, "affinity": -20, "defense": 0, "rarity": 3, "slots": [], "kinsect_level": 2, "element": ["Ice", 10], "rampage_skills": ["Affinity Boost I", "Ice Boost I", "Brutal Strike"], "crafting_list": {"Zenny": 10500, "Goss Harag Brace": 3, "Goss Harag Fur": 3, "Goss harag Claw": 2, "Massive Bone": 2}},
	{"name": "Gossglaive II", "rank": "High", "raw": 210, "affinity": -20, "defense": 0, "rarity": 6, "slots": [2], "kinsect_level": 4, "element": ["Ice", 12], "rampage_skills": ["Affinity Boost I", "Ice Boost II", "Brutal Strike"], "crafting_list": {"Zenny": 42000, "Goss Harag Brace +": 3, "Goss Harag Fur +": 4, "Freezer Sac": 3, "Great Stoutbone": 3}},
	{"name": "Abominable Glaive", "rank": "High", "raw": 230, "affinity": -20, "defense": 0, "rarity": 6, "slots": [2], "kinsect_level": 5, "element": ["Ice", 15], "rampage_skills": ["Affinity Boost II", "Ice Boost III", "Brutal Strike"], "crafting_list": {"Zenny": 56000, "Points": "Goss Harag+ x12 Points", "Elder Dragon Bone": 3, "Goss Harag Bile": 1}},
	{"name": "Pukei Rod I", "rank": "Low", "raw": 100, "affinity": 0, "defense": 0, "rarity": 2, "slots": [], "kinsect_level": 3, "element": ["Poison", 24], "rampage_skills": ["Attack Boost II", "Dulling Strike", "Poison Boost I"], "crafting_list": {"Zenny": 2600, "Pukei-Pukei Scale": 3, "Pukei-Pukei Quill": 2, "Monster Bone L": 2}},
	{"name": "Pukei Rod II", "rank": "High", "raw": 150, "affinity": 0, "defense": 0, "rarity": 4, "slots": [2, 1], "kinsect_level": 4, "element": ["Poison", 27], "rampage_skills": ["Attack Boost III", "Dulling Strike", "Poison Boost I"], "crafting_list": {"Zenny": 10400, "Points": "Pukei-Pukei x8 Points", "Quality Bone": 3, "Pukei-Pukei": 0}},
	{"name": "Datura Pike", "rank": "High", "raw": 170, "affinity": 0, "defense": 0, "rarity": 5, "slots": [2, 1], "kinsect_level": 5, "element": ["Poison", 30], "rampage_skills": ["Attack Boost III", "Dulling Strike", "Poison Boost II"], "crafting_list": {"Zenny": 20000, "Pukei-Pukei Scale +": 3, "Pukei-Pukei Wing": 2, "Pukei-Pukei Sac +": 2, "Bird Wyvern Gem": 1}},
	{"name": "Amber Piton I", "rank": "Low", "raw": 90, "affinity": 15, "defense": 0, "rarity": 2, "slots": [], "kinsect_level": 2, "element": ["Ice", 16], "rampage_skills": ["Attack Boost II", "Affinity Boost II", "Iceblight Exploit"], "crafting_list": {"Zenny": 2600, "Amber Fang": 2, "Barioth Shell": 2, "Barioth Spike": 3}},
	{"name": "Amber Piton II", "rank": "High", "raw": 160, "affinity": 15, "defense": 0, "rarity": 5, "slots": [1, 1, 1], "kinsect_level": 5, "element": ["Ice", 22], "rampage_skills": ["Attack Boost III", "Affinity Boost II", "Iceblight Exploit"], "crafting_list": {"Zenny": 26000, "Amber Fang +": 2, "Barioth Carapace": 3, "Barioth Tail": 2, "Freezer Sac": 3}},
	{"name": "Fenrir Storm", "rank": "High", "raw": 190, "affinity": 15, "defense": 0, "rarity": 6, "slots": [1, 1, 1], "kinsect_level": 6, "element": ["Ice", 25], "rampage_skills": ["Attack Boost IV", "Affinity Boost II", "Iceblight Exploit"], "crafting_list": {"Zenny": 39000, "Points": "Barioth+ x12 Points", "Goss Harag Claw +": 2, "Barioth Pelt +": 2, "Wyvern Gem": 1}},
	{"name": "Royal Bloom I", "rank": "Low", "raw": 80, "affinity": 0, "defense": 0, "rarity": 2, "slots": [], "kinsect_level": 2, "element": ["Water", 20], "rampage_skills": ["Attack Boost II", "Water Boost I"], "crafting_list": {"Zenny": 1300, "Royal Ludroth Crest": 2, "Spongy Hide": 2, "Jumbo Bone": 3}},
	{"name": "Royal Bloom II", "rank": "Low", "raw": 130, "affinity": 0, "defense": 0, "rarity": 3, "slots": [], "kinsect_level": 3, "element": ["Water", 25], "rampage_skills": ["Attack Boost II", "Water Boost I"], "crafting_list": {"Zenny": 6500, "Points": "Ludroth x8 Points", "Almudron Claw": 2, "Royal Ludroth Tail": 1}},
	{"name": "Bloom Royale", "rank": "High", "raw": 160, "affinity": 0, "defense": 0, "rarity": 5, "slots": [2, 1, 1], "kinsect_level": 5, "element": ["Water", 33], "rampage_skills": ["Attack Boost III", "Water Boost II"], "crafting_list": {"Zenny": 20000, "Royal Ludroth Crest +": 3, "Royal Ludroth Claw +": 3, "Torrent Sac": 2, "Wyvern Gem": 1}},
	{"name": "Royal Bolt Scepter I", "rank": "Low", "raw": 120, "affinity": 0, "defense": 0, "rarity": 3, "slots": [], "kinsect_level": 3, "element": ["Thunder", 20], "rampage_skills": ["Attack Boost I", "Thunder Boost I", "Anti-Aquatic Species"], "crafting_list": {"Zenny": 4200, "Zinogre Shocker": 2, "Zinogre Shell": 3, "Fulgurbug": 3}},
	{"name": "Royal Bolt Scepter II", "rank": "High", "raw": 190, "affinity": 0, "defense": 0, "rarity": 5, "slots": [1, 1], "kinsect_level": 8, "element": ["Thunder", 23], "rampage_skills": ["Attack Boost II", "Thunder Boost II", "Anti-Aquatic Species"], "crafting_list": {"Zenny": 28000, "Zinogre Shocker +": 3, "Zinogre Carapace": 3, "Zinogre Horn +": 2, "Zinogre Tail": 2}},
	{"name": "Despot's Twinbolt", "rank": "High", "raw": 200, "affinity": 0, "defense": 0, "rarity": 6, "slots": [1, 1], "kinsect_level": 8, "element": ["Thunder", 25], "rampage_skills": ["Attack Boost II", "Thunder Boost II", "Anti-Aquatic Species"], "crafting_list": {"Zenny": 56000, "Points": "Zinogre+ x10 Points", "Narwa Carapace": 3, "Zinogre Jasper": 1}},
	{"name": "Hortadent I", "rank": "Low", "raw": 90, "affinity": 0, "defense": 0, "rarity": 1, "slots": [], "kinsect_level": 3, "element": null, "rampage_skills": ["Attack Boost II", "Kinsect Level Boost", "Small Monster Exploit"], "crafting_list": {"Zenny": 990, "Monster Bone M": 3, "Altaroth Jaw": 2, "Altaroth Stomach": 2}},
	{"name": "Hortadent II", "rank": "Low", "raw": 100, "affinity": 0, "defense": 0, "rarity": 2, "slots": [], "kinsect_level": 4, "element": null, "rampage_skills": ["Attack Boost III", "Kinsect Level Boost", "Small Monster Exploit"], "crafting_list": {"Zenny": 1100, "Points": "Neopteron x8 Points", "Eroded Skeleton": 3, "Sharp Claw": 3}},
	{"name": "Hortadent Brada", "rank": "High", "raw": 160, "affinity": 0, "defense": 0, "rarity": 4, "slots": [2, 1, 1], "kinsect_level": 5, "element": null, "rampage_skills": ["Attack Boost IV", "Kinsect Level Boost", "Small Monster Exploit"], "crafting_list": {"Zenny": 8800, "Points": "Neopteron+ x10 Points", "Quality Stomach": 2, "Piercing Claw": 3, "Monster Broth": 3}},
	{"name": "Rielle Nulo I", "rank": "Low", "raw": 80, "affinity": 0, "defense": 0, "rarity": 2, "slots": [], "kinsect_level": 3, "element": null, "rampage_skills": ["Attack Boost II", "Affinity Boost I", "Silkbind Boost"], "crafting_list": {"Zenny": 1650, "Lightcrystal": 2, "Bnahabra Wing": 3, "Bnahabra Shell": 3}},
	{"name": "Rielle Nulo II", "rank": "Low", "raw": 100, "affinity": 0, "defense": 0, "rarity": 2, "slots": [], "kinsect_level": 4, "element": null, "rampage_skills": ["Attack Boost II", "Affinity Boost I", "Silkbind Boost"], "crafting_list": {"Zenny": 2200, "Points": "Neopteron x8 Points", "Rachnoid Silk": 2, "Dragonite Ore": 2}},
	{"name": "Rielle Unu", "rank": "Low", "raw": 140, "affinity": 0, "defense": 0, "rarity": 3, "slots": [], "kinsect_level": 4, "element": null, "rampage_skills": ["Attack Boost III", "Affinity Boost II", "Silkbind Boost"], "crafting_list": {"Zenny": 5500, "Points": "Neopteron x10 Points", "Twisted Horn": 1, "Bnahabra Shell": 3}},
	{"name": "Rielle Nulo Red I", "rank": "High", "raw": 150, "affinity": 0, "defense": 0, "rarity": 4, "slots": [3, 1], "kinsect_level": 5, "element": ["Fire", 14], "rampage_skills": ["Attack Boost III", "Fire Boost II", "Silkbind Boost"], "crafting_list": {"Zenny": 13200, "Bnahabra Carapace": 4, "Monster Broth": 2, "Piercing Claw": 3, "Inferno Sac": 2}},
	{"name": "Rielle Nulo Red II", "rank": "High", "raw": 160, "affinity": 0, "defense": 0, "rarity": 5, "slots": [3, 1], "kinsect_level": 6, "element": ["Fire", 16], "rampage_skills": ["Attack Boost III", "Fire Boost II", "Silkbind Boost"], "crafting_list": {"Zenny": 13200, "Points": "Neopteron+ x10 Points", "Novacrystal": 2, "Aknosom Crest +": 2}},
	{"name": "Rielle Vermiglio", "rank": "High", "raw": 180, "affinity": 0, "defense": 0, "rarity": 6, "slots": [3, 1], "kinsect_level": 8, "element": ["Fire", 20], "rampage_skills": ["Attack Boost IV", "Fire Boost III", "Silkbind Boost"], "crafting_list": {"Zenny": 33000, "Points": "Neopteron+ x12 Points", "Rakna-Kadaki Glowgut": 2, "Monster Broth": 4}},
	{"name": "Rielle Nulo Black I", "rank": "High", "raw": 140, "affinity": 0, "defense": 0, "rarity": 4, "slots": [3, 1], "kinsect_level": 5, "element": ["Dragon", 15], "rampage_skills": ["Attack Boost III", "Dragon Boost II", "Silkbind Boost"], "crafting_list": {"Zenny": 13200, "Bnahabra Carapace": 4, "Monster Broth": 2, "Quality Stomach": 2, "Dragonbone Relic": 3}},
	{"name": "Rielle Nulo Black II", "rank": "High", "raw": 160, "affinity": 0, "defense": 0, "rarity": 5, "slots": [3, 1], "kinsect_level": 6, "element": ["Dragon", 17], "rampage_skills": ["Attack Boost III", "Dragon Boost II", "Silkbind Boost"], "crafting_list": {"Zenny": 13200, "Points": "Neopteron+ x10 Points", "Novacrystal": 2, "Remobra Hide +": 3}},
	{"name": "Rielle Nerissimo", "rank": "High", "raw": 180, "affinity": 0, "defense": 0, "rarity": 6, "slots": [3, 1], "kinsect_level": 8, "element": ["Dragon", 20], "rampage_skills": ["Attack Boost IV", "Dragon Boost III", "Silkbind Boost"], "crafting_list": {"Zenny": 33000, "Points": "Neopteron+ x12 Points", "Rakna-Kadaki Carapace": 2, "Monster Broth": 4}},
	{"name": "Rielle Nulo White I", "rank": "Low", "raw": 120, "affinity": 0, "defense": 0, "rarity": 3, "slots": [], "kinsect_level": 4, "element": ["Ice", 12], "rampage_skills": ["Attack Boost III", "Ice Boost II", "Silkbind Boost"], "crafting_list": {"Zenny": 5500, "Goss Harag Claw": 2, "Bnahabra Wing": 3, "Frost Sac": 2}},
	{"name": "Rielle Nulo White II", "rank": "High", "raw": 160, "affinity": 0, "defense": 0, "rarity": 5, "slots": [3, 1], "kinsect_level": 6, "element": ["Ice", 16], "rampage_skills": ["Attack Boost III", "Ice Boost II", "Silkbind Boost"], "crafting_list": {"Zenny": 13200, "Points": "Neopteron+ x10 Points", "Novacrystal": 2, "Lagombi Frozenclaw": 3}},
	{"name": "Rielle Unu White", "rank": "High", "raw": 170, "affinity": 0, "defense": 0, "rarity": 6, "slots": [3, 1], "kinsect_level": 8, "element": ["Ice", 18], "rampage_skills": ["Attack Boost IV", "Ice Boost III", "Silkbind Boost"], "crafting_list": {"Zenny": 22000, "Points": "Neopteron+ x12 Points", "Freezer Sac": 2, "Monster Broth": 4}},
	{"name": "Rielle Nulo Green I", "rank": "Low", "raw": 100, "affinity": 0, "defense": 0, "rarity": 2, "slots": [], "kinsect_level": 4, "element": ["Paralysis", 15], "rampage_skills": ["Attack Boost II", "Paralysis Boost I", "SilkBind Boost"], "crafting_list": {"Zenny": 2200, "Paralysis Sac": 2, "Bnahabra Stinger": 3, "Lightcrystal": 1}},
	{"name": "Rielle Nulo Green II", "rank": "High", "raw": 130, "affinity": 0, "defense": 0, "rarity": 5, "slots": [1, 1, 1], "kinsect_level": 6, "element": ["Paralysis", 18], "rampage_skills": ["Attack Boost II", "Paralysis Boost I", "SilkBind Boost"], "crafting_list": {"Zenny": 13200, "Points": "Neopteron+ x10 Points", "Novacrystal": 2, "Omniplegia Sac": 2}},
	{"name": "Rielle Unu Green", "rank": "High", "raw": 170, "affinity": 0, "defense": 0, "rarity": 6, "slots": [1, 1, 1], "kinsect_level": 7, "element": ["Paralysis", 20], "rampage_skills": ["Attack Boost III", "Paralysis Boost I", "SilkBind Boost"], "crafting_list": {"Zenny": 22000, "Points": "Neopteron+ x12 Points", "Zinogre Claw +": 2, "Monster Broth": 4}},
	{"name": "Sinister Staff I", "rank": "Low", "raw": 130, "affinity": 0, "defense": 0, "rarity": 3, "slots": [], "kinsect_level": 3, "element": ["Blast", 13], "rampage_skills": ["Attack Boost II", "Blast Boost I", "Magnamalo Soul"], "crafting_list": {"Zenny": 7500, "Magnamalo Blade": 2, "Magnamalo Shell": 3, "Magnamalo Scute": 2, "Magna Ghostprism": 2}},
	{"name": "Sinister Staff II", "rank": "Low", "raw": 140, "affinity": 0, "defense": 0, "rarity": 3, "slots": [], "kinsect_level": 3, "element": ["Blast", 15], "rampage_skills": ["Attack Boost III", "Blast Boost I", "Magnamalo Soul"], "crafting_list": {"Zenny": 8000, "Commendation": 1, "Magnamalo Tail": 2, "Magnamalo Plate": 1}},
	{"name": "Sinister Shadowstaff", "rank": "High", "raw": 200, "affinity": 0, "defense": 0, "rarity": 6, "slots": [2, 1], "kinsect_level": 7, "element": ["Blast", 20], "rampage_skills": ["Attack Boost III", "Blast Boost II", "Magnamalo Soul"], "crafting_list": {"Zenny": 45000, "Magnamalo Blade +": 2, "Magnamalo Shell +": 3, "Magnamalo Scute +": 2, "Purple Magna Orb": 1}},
	{"name": "Metal Mauler I", "rank": "High", "raw": 180, "affinity": -20, "defense": 0, "rarity": 5, "slots": [], "kinsect_level": 4, "element": ["Thunder", 18], "rampage_skills": ["Affinity Boost I", "Thunder Boost I", "Dulling Strike"], "crafting_list": {"Zenny": 27000, "Rajang Blackfur": 3, "Rajang Horn +": 1, "Rajang Fang +": 3, "Great Stoutbone": 2}},
	{"name": "Metal Mauler II", "rank": "High", "raw": 200, "affinity": -20, "defense": 0, "rarity": 6, "slots": [3], "kinsect_level": 5, "element": ["Thunder", 20], "rampage_skills": ["Affinity Boost I", "Thunder Boost II", "Dulling Strike"], "crafting_list": {"Zenny": 45000, "High Commendation": 1, "Rajang Claw +": 3, "Gold Rajang Pelt": 1}},
	{"name": "Azure Elder Glaive I", "rank": "High", "raw": 180, "affinity": 0, "defense": 0, "rarity": 5, "slots": [], "kinsect_level": 4, "element": ["Dragon", 10], "rampage_skills": ["Dragon Boost III", "Anti-Aerial Species", "Defense Boost I"], "crafting_list": {"Zenny": 45000, "Ibushi Horn +": 1, "Ibushi Carapace": 2, "Ibushi Bluespike": 2, "Ibushi Windsac": 2}},
	{"name": "Azure Elder Glaive II", "rank": "High", "raw": 200, "affinity": 0, "defense": 0, "rarity": 6, "slots": [], "kinsect_level": 5, "element": ["Dragon", 12], "rampage_skills": ["Dragon Boost III", "Anti-Aerial Species", "Ibushi Soul"], "crafting_list": {"Zenny": 60000, "Points": "Ibushi+ x10 Points", "Elder Dragon Bone": 3, "Wind Serpent Orb": 1}},
	{"name": "Thunderbolt Glaive I", "rank": "High", "raw": 170, "affinity": 0, "defense": 0, "rarity": 6, "slots": [], "kinsect_level": 7, "element": ["Thunder", 36], "rampage_skills": ["Attack Boost II", "Anti-Aerial Species", "Narwa Soul"], "crafting_list": {"Zenny": 75000, "Narwa Carapace": 2, "Narwa Horn +": 1, "Narwa Tentacle": 2, "Narwa Sparksac": 2}},
	{"name": "Daora's Entom I", "rank": "High", "raw": 170, "affinity": 0, "defense": 0, "rarity": 6, "slots": [1], "kinsect_level": 6, "element": ["Ice", 34], "rampage_skills": ["Attack Boost II", "Ice Boost I", "Kushala Daora Soul"], "crafting_list": {"Zenny": 60000, "Daora Dragon Scale +": 4, "Daora Horn +": 2, "Daora Tail": 2, "Elder Dragon Bone": 3}},
	{"name": "Caster's Rod I", "rank": "High", "raw": 180, "affinity": 0, "defense": 0, "rarity": 6, "slots": [2, 1, 1], "kinsect_level": 6, "element": ["Poison", 35], "rampage_skills": ["Attack Boost II", "Defense Boost III", "Chameleos Soul"], "crafting_list": {"Zenny": 60000, "Chameleos Hide +": 4, "Chameleos Spike": 2, "Chameleos Tail": 2, "Elder Dragon Blood": 2}},
	{"name": "Deathport Staff I", "rank": "Low", "raw": 100, "affinity": 0, "defense": 15, "rarity": 2, "slots": [], "kinsect_level": 4, "element": ["Dragon", 16], "rampage_skills": ["Attack Boost II", "Dragon Boost I", "Dragon Exploit"], "crafting_list": {"Zenny": 3300, "Sinister Cloth": 1, "Dragonhusk Shard": 2, "Bishaten Horn": 2}},
	{"name": "Deathport Staff II", "rank": "High", "raw": 160, "affinity": 0, "defense": 15, "rarity": 4, "slots": [2, 2], "kinsect_level": 5, "element": ["Dragon", 20], "rampage_skills": ["Attack Boost II", "Dragon Boost II", "Dragon Exploit"], "crafting_list": {"Zenny": 8800, "Dragonbone Relic": 2, "Sinister Cloth": 3, "Piercing Claw": 3, "Goss harag Horn": 2}},
	{"name": "Garamorse", "rank": "High", "raw": 210, "affinity": 0, "defense": 20, "rarity": 5, "slots": [2, 2], "kinsect_level": 7, "element": ["Dragon", 24], "rampage_skills": ["Attack Boost III", "Dragon Boost II", "Dragon Exploit"], "crafting_list": {"Zenny": 22000, "Sinister Darkcloth": 1, "Monster Hardbone": 3, "Anjanath Nosebone +": 2}},
	{"name": "Magia Pitareen I", "rank": "Low", "raw": 70, "affinity": 0, "defense": 5, "rarity": 2, "slots": [], "kinsect_level": 3, "element": ["Blast", 20], "rampage_skills": ["Attack Boost II", "Defense Boost I", "Silkbind Boost"], "crafting_list": {"Zenny": 1650, "Blossom Cricket": 1, "Lightcrystal": 2, "Bombadgy Igniter": 3}},
	{"name": "Magia Pitareen II", "rank": "Low", "raw": 100, "affinity": 0, "defense": 5, "rarity": 3, "slots": [], "kinsect_level": 4, "element": ["Blast", 25], "rampage_skills": ["Attack Boost III", "Defense Boost I", "Silkbind Boost"], "crafting_list": {"Zenny": 3300, "Mizutsune Fin": 2, "Monster Fluid": 3, "Blossom Cricket": 2}},
	{"name": "Magia Pitareen III", "rank": "High", "raw": 150, "affinity": 0, "defense": 5, "rarity": 5, "slots": [1, 1, 1], "kinsect_level": 5, "element": ["Blast", 29], "rampage_skills": ["Attack Boost IV", "Defense Boost II", "Silkbind Boost"], "crafting_list": {"Zenny": 13200, "Novacrystal": 2, "Monster Broth": 3, "Blossom Cricket": 3}},
	{"name": "Magia Crescent", "rank": "High", "raw": 190, "affinity": 0, "defense": 5, "rarity": 6, "slots": [1, 1, 1], "kinsect_level": 8, "element": ["Blast", 33], "rampage_skills": ["Attack Boost I", "Affinity Boost II", "Defense Boost I"], "crafting_list": {"Zenny": 44000, "Teostra Powder": 2, "Rakna-Kadaki Sharpclaw": 2, "Blossom Cricket": 4}},
	{"name": "Brush Glaive I", "rank": "High", "raw": 200, "affinity": -10, "defense": 0, "rarity": 5, "slots": [3], "kinsect_level": 4, "element": ["Water", 8], "rampage_skills": ["Water Boost II", "Dulling Strike", "Master Rider"], "crafting_list": {"Zenny": 33000, "Bubblefoam +": 2, "Lagombi Pelt +": 3, "Firecell Stone": 3, "Kamura Ticket": 2}},
	{"name": "Brush Glaive II", "rank": "High", "raw": 210, "affinity": -10, "defense": 0, "rarity": 6, "slots": [3], "kinsect_level": 5, "element": ["Water", 9], "rampage_skills": ["Water Boost III", "Dulling Strike", "Master Rider"], "crafting_list": {"Zenny": 33000, "Goss Harag Fur +": 2, "Torrent Sac": 3, "Kamura Ticket": 3}},
	{"name": "Watercolor Glaive", "rank": "High", "raw": 220, "affinity": -10, "defense": 0, "rarity": 6, "slots": [3], "kinsect_level": 6, "element": ["Water", 10], "rampage_skills": ["Water Boost IV", "Dulling Strike", "Master Rider"], "crafting_list": {"Zenny": 44000, "Elder Dragon Blood": 2, "Almudron Fin +": 3, "Kamura Ticket": 4}},
	{"name": "Rampage Glaive I", "rank": "High", "raw": 150, "affinity": 0, "defense": 0, "rarity": 4, "slots": [], "kinsect_level": 3, "element": null, "rampage_skills": ["Any"], "crafting_list": {"Zenny": 15000, "Apex Beastclaw": 1, "Arzuros Brace +": 2, "Guild Ticket": 1}},
	{"name": "Rampage Glaive II", "rank": "High", "raw": 170, "affinity": 0, "defense": 0, "rarity": 5, "slots": [], "kinsect_level": 3, "element": null, "rampage_skills": ["Any"], "crafting_list": {"Zenny": 20000, "Apex Venom Spike": 1, "Bishaten Talon +": 2, "Defender Ticket 5": 1}},
	{"name": "Rampage Glaive III", "rank": "High", "raw": 180, "affinity": 0, "defense": 0, "rarity": 5, "slots": [], "kinsect_level": 3, "element": null, "rampage_skills": ["Any"], "crafting_list": {"Zenny": 25000, "Ibushi Carapace": 1, "Rathalos Wing": 3, "Defender Ticket 6": 1}},
	{"name": "Rampage Glaive IV", "rank": "High", "raw": 190, "affinity": 0, "defense": 0, "rarity": 6, "slots": [], "kinsect_level": 3, "element": null, "rampage_skills": ["Any"], "crafting_list": {"Zenny": 30000, "Apex Bubblefoam": 1, "Rakna-Kadaki Spike": 1, "Defender Ticket 7": 1}},
	{"name": "Rampage Glaive V", "rank": "High", "raw": 200, "affinity": 0, "defense": 0, "rarity": 6, "slots": [], "kinsect_level": 3, "element": null, "rampage_skills": ["Any"], "crafting_list": {"Zenny": 40000, "Apex Blaze Sac": 1, "Apex Curlhorn": 1, "Defender Ticket 8": 1}},
	{"name": "Curved Naganagi", "rank": "High", "raw": 190, "affinity": 15, "defense": 0, "rarity": 6, "slots": [2, 1], "kinsect_level": 7, "element": ["Water", 20], "rampage_skills": ["Attack Boost III", "Affinity Boost II", "Water Boost II"], "crafting_list": {"Zenny": 56000, "Scale of Origin": 3, "Mizutsune Water Orb": 1}},
	{"name": "Redwing Glaive", "rank": "High", "raw": 160, "affinity": 0, "defense": 0, "rarity": 6, "slots": [2], "kinsect_level": 5, "element": ["Dragon", 35], "rampage_skills": ["Attack Boost III", "Wyvern Exploit", "Valstrax Soul"], "crafting_list": {"Zenny": 75000, "Rouge Spikewing": 3, "Gleaming Shell": 3, "Valstrax Tail": 2, "Firecell Stone": 5}},
	{"name": "Abyssal Gale Glaive", "rank": "High", "raw": 210, "affinity": 0, "defense": 0, "rarity": 7, "slots": [], "kinsect_level": 6, "element": ["Dragon", 14], "rampage_skills": ["Dragon Boost IV", "Anti-Aerial Species", "Ibushi Soul"], "crafting_list": {"Zenny": 80000, "Orb of Origin": 1, "Narwa Hide +": 1, "Ibushi Claw +": 1}},
	{"name": "Abyssal Storm Glaive", "rank": "High", "raw": 180, "affinity": 0, "defense": 0, "rarity": 7, "slots": [], "kinsect_level": 8, "element": ["Thunder", 38], "rampage_skills": ["Attack Boost III", "Anti-Aerial Species", "Narwa Soul"], "crafting_list": {"Zenny": 80000, "Orb of Origin": 1, "Thunder Serpent Orb": 1, "Ibushi Hide +": 3}},
	{"name": "Daora's Tethidine", "rank": "High", "raw": 180, "affinity": 0, "defense": 0, "rarity": 7, "slots": [1], "kinsect_level": 7, "element": ["Ice", 36], "rampage_skills": ["Attack Boost III", "Ice Boost II", "Kushala Daora Soul"], "crafting_list": {"Zenny": 75000, "Rouge Spikewing": 1, "Daora Claw +": 3, "Daora Gem": 1}},
	{"name": "Hazy Caster", "rank": "High", "raw": 190, "affinity": 0, "defense": 0, "rarity": 7, "slots": [2, 1, 1], "kinsect_level": 6, "element": ["Poison", 38], "rampage_skills": ["Attack Boost III", "Defense Boost III", "Chameleos Soul"], "crafting_list": {"Zenny": 75000, "Gleaming Shell": 1, "Chameleos Wing": 3, "Chameleos Gem": 1}},
	{"name": "Metalmangler", "rank": "High", "raw": 220, "affinity": -20, "defense": 0, "rarity": 7, "slots": [3], "kinsect_level": 6, "element": ["Thunder", 22], "rampage_skills": ["Affinity Boost II", "Thunder Boost II", "Dulling Strike"], "crafting_list": {"Zenny": 60000, "Horn of Origin": 1, "Rajang Tail": 2}},
	{"name": "Tyrant Rod", "rank": "High", "raw": 230, "affinity": -10, "defense": 0, "rarity": 7, "slots": [], "kinsect_level": 6, "element": null, "rampage_skills": ["Attack Boost III", "Defense Boost II", "Kinsect Level Boost"], "crafting_list": {"Zenny": 70000, "Horn of Origin": 1, "Diablos Medulla": 1}},
	{"name": "Reddnaught Shuma", "rank": "High", "raw": 170, "affinity": 0, "defense": 0, "rarity": 7, "slots": [2], "kinsect_level": 5, "element": ["Dragon", 38], "rampage_skills": ["Attack Boost III", "Wyvern Exploit", "Valstrax Soul"], "crafting_list": {"Zenny": 90000, "Valstrax Claw +": 3, "Red Serpent Orb": 1}},
	{"name": "Rampage Glaive S", "rank": "High", "raw": 210, "affinity": 0, "defense": 0, "rarity": 7, "slots": [], "kinsect_level": 3, "element": null, "rampage_skills": ["--"], "crafting_list": {"Zenny": 50000, "Apex Shockshell": 2, "Apex Blaze Sac": 1, "Defender Ticket 9": 1}},
	{"name": "Defender Glaive I", "rank": "Low", "raw": 110, "affinity": 0, "defense": 30, "rarity": 1, "slots": [], "kinsect_level": 3, "element": null, "rampage_skills": [], "crafting_list": {"Zenny": 600, "Points": "Bone 1 pts"}},
	{"name": "Champion Glaive", "rank": "Low", "raw": 150, "affinity": 0, "defense": 30, "rarity": 2, "slots": [], "kinsect_level": 4, "element": null, "rampage_skills": [], "crafting_list": {"Zenny": 2000, "Points": "Bone 1 pts"}},
	{"name": "Champion Glaive II", "rank": "High", "raw": 190, "affinity": 0, "defense": 30, "rarity": 4, "slots": [], "kinsect_level": 4, "element": null, "rampage_skills": [], "crafting_list": {"Zenny": 6000, "Points": "Bone+ 1 pts"}},
	{"name": "Champion Glaive III", "rank": "High", "raw": 210, "affinity": 0, "defense": 30, "rarity": 4, "slots": [], "kinsect_level": 5, "element": null, "rampage_skills": [], "crafting_list": {"Zenny": 7000, "Points": "Bone+ 1 pts"}},
	{"name": "Guardian Glaive", "rank": "High", "raw": 230, "affinity": 0, "defense": 30, "rarity": 5, "slots": [], "kinsect_level": 6, "element": null, "rampage_skills": [], "crafting_list": {"Zenny": 8000, "Points": "Bone+ 1 pts"}},
	{"name": "Kamura Warrior Glaive", "rank": "Master", "raw": 250, "affinity": 0, "defense": 0, "rarity": 8, "slots": [1, 12], "kinsect_level": 8, "element": null, "rampage_skills": [], "crafting_list": {"Zenny": 18000, "Eltalite Ore": 8, "Tough Claw": 5, "Awegite": 1}},
	{"name": "Kamura Warrior Glaive +", "rank": "Master", "raw": 300, "affinity": 0, "defense": 0, "rarity": 8, "slots": [1, 12], "kinsect_level": 0, "element": null, "rampage_skills": [], "crafting_list": {"Zenny": 24000, "Centuria Ore": 2, "Jyuratodus Cortex": 2, "Large Wyvern Gem": 1, "Points": "MR Bone 15 pts"}},
	{"name": "Fine Kamura Glaive", "rank": "Master", "raw": 330, "affinity": 0, "defense": 0, "rarity": 10, "slots": [2, 12], "kinsect_level": 4, "element": null, "rampage_skills": [], "crafting_list": {"Zenny": 60000, "Afflicted Pelt": 7, "Points": "MR Bone 20 pts"}},
	{"name": "Duke's Scepter", "rank": "Master", "raw": 320, "affinity": 0, "defense": 0, "rarity": 9, "slots": [11], "kinsect_level": 4, "element": ["Dragon", 20], "rampage_skills": [], "crafting_list": {"Zenny": 52000, "Malzeno Cortex": 3, "Bloody Parasite": 3, "Malzeno Hardfang": 3, "Malzeno Fellwing": 2}},
	{"name": "Twilight Repose", "rank": "Master", "raw": 270, "affinity": 40, "defense": 0, "rarity": 8, "slots": [2, 11], "kinsect_level": 9, "element": null, "rampage_skills": [], "crafting_list": {"Zenny": 24000, "Points": "Nargacuga Cutwing+ x2", "Nargacuga Shard": 5, "Eltalite Ore": 3}},
	{"name": "Twilight Repose +", "rank": "Master", "raw": 280, "affinity": 40, "defense": 0, "rarity": 9, "slots": [2, 11], "kinsect_level": 3, "element": null, "rampage_skills": [], "crafting_list": {"Zenny": 52000, "Malzeno Hardfang": 2, "Nargacuga Mantle": 1, "Points": "MR Nargacuga 15 pts"}},
	{"name": "Avidya Scythe", "rank": "Master", "raw": 300, "affinity": 40, "defense": 0, "rarity": 10, "slots": [2, 11], "kinsect_level": 4, "element": null, "rampage_skills": [], "crafting_list": {"Zenny": 60000, "Afflicted Fang": 7, "Points": "MR Nargacuga 30 pts"}},
	{"name": "Curved Naganagi +", "rank": "Master", "raw": 300, "affinity": 15, "defense": 0, "rarity": 9, "slots": [2, 1, 12], "kinsect_level": 2, "element": ["Water", 26], "rampage_skills": [], "crafting_list": {"Zenny": 54000, "Mizutsune Purplefell": 4, "Mizutsune Silkfin": 4, "Purple Mizutsune Tail": 2, "Dragonbone Artifact": 1}},
	{"name": "Eventide Kazanagi", "rank": "Master", "raw": 310, "affinity": 15, "defense": 0, "rarity": 9, "slots": [2, 1, 12], "kinsect_level": 3, "element": ["Water", 28], "rampage_skills": [], "crafting_list": {"Zenny": 52000, "Large Elder Dragon Bone": 3, "Mizutsune Mantle": 1, "Points": "MR Mizutsune 10 pts"}},
	{"name": "Eventide Kazanagi +", "rank": "Master", "raw": 320, "affinity": 15, "defense": 0, "rarity": 10, "slots": [2, 1, 12], "kinsect_level": 4, "element": ["Water", 31], "rampage_skills": [], "crafting_list": {"Zenny": 60000, "Afflicted Claw": 5, "Afflicted Scale": 5, "Points": "MR Mizutsune 30 pts"}},
	{"name": "Illusory Frilled Jab +", "rank": "Master", "raw": 260, "affinity": 0, "defense": 0, "rarity": 8, "slots": [1, 1, 12], "kinsect_level": 8, "element": ["Sleep", 19], "rampage_skills": [], "crafting_list": {"Zenny": 16000, "Somnacanth Dreamtalon": 4, "Somnacanth Cortex": 3, "Somna Dream Powder": 2}},
	{"name": "Nightmare Frilled Jab", "rank": "Master", "raw": 300, "affinity": 0, "defense": 0, "rarity": 8, "slots": [1, 1, 12], "kinsect_level": 0, "element": ["Sleep", 22], "rampage_skills": [], "crafting_list": {"Zenny": 24000, "Almudron Hardclaw": 2, "Somnacanth Wild Fin": 2, "Large Wyvern Gem": 1, "Points": "MR Somnacanth 8 pts"}},
	{"name": "Nightmare Frilled Jab +", "rank": "Master", "raw": 340, "affinity": 0, "defense": 0, "rarity": 10, "slots": [2, 1, 12], "kinsect_level": 4, "element": ["Sleep", 26], "rampage_skills": [], "crafting_list": {"None": 0, "Afflicted Shell": 7, "Points": "MR Somnacanth 30 pts"}},
	{"name": "Bloom Snow Jab", "rank": "Master", "raw": 280, "affinity": 0, "defense": 0, "rarity": 8, "slots": [1, 1, 12], "kinsect_level": 0, "element": ["Ice", 47], "rampage_skills": [], "crafting_list": {"Zenny": 36000, "Auroracanth Iceclaw": 6, "Auroracanth Fin": 5, "Cryo Sac": 3, "Dragonbone Artifact": 1}},
	{"name": "Bloom Snow Jab +", "rank": "Master", "raw": 310, "affinity": 0, "defense": 0, "rarity": 9, "slots": [1, 1, 12], "kinsect_level": 3, "element": ["Ice", 52], "rampage_skills": [], "crafting_list": {"Zenny": 52000, "Daora Hardclaw": 2, "Auroracanth Fin": 2, "Large Wyvern Gem": 1, "Points": "MR Aurora Somnacanth 8 pts"}},
	{"name": "Flicker Blizzard Jab", "rank": "Master", "raw": 320, "affinity": 0, "defense": 0, "rarity": 10, "slots": [1, 1, 12], "kinsect_level": 4, "element": ["Ice", 57], "rampage_skills": [], "crafting_list": {"Zenny": 60000, "Afflicted Claw": 7, "Points": "MR Aurora Somnacanth 30 pts"}},
	{"name": "Tigerclaw Glaive +", "rank": "Master", "raw": 320, "affinity": -10, "defense": 0, "rarity": 9, "slots": [1, 12], "kinsect_level": 2, "element": null, "rampage_skills": [], "crafting_list": {"Zenny": 36000, "Tigrex Hardclaw": 3, "Tigrex Cortex": 4, "Tigrex Lash": 1}},
	{"name": "Great Tigerclaw Glaive", "rank": "Master", "raw": 330, "affinity": -10, "defense": 0, "rarity": 9, "slots": [1, 12], "kinsect_level": 3, "element": null, "rampage_skills": [], "crafting_list": {"Zenny": 52000, "Fire Dragon Hardclaw": 3, "Tigrex Mantle": 1, "Points": "MR Tigrex 15 pts"}},
	{"name": "Great Tigerclaw Glaive +", "rank": "Master", "raw": 340, "affinity": -10, "defense": 0, "rarity": 10, "slots": [1, 12], "kinsect_level": 4, "element": null, "rampage_skills": [], "crafting_list": {"Zenny": 60000, "Afflicted Claw": 5, "Afflicted Shell": 5, "Points": "MR Tigrex 30 pts"}},
	{"name": "Leapfrog +", "rank": "Master", "raw": 250, "affinity": 0, "defense": 20, "rarity": 8, "slots": [2, 13], "kinsect_level": 8, "element": ["Water", 18], "rampage_skills": [], "crafting_list": {"Zenny": 12000, "Tetranadon Greatbeak": 2, "Heavy Tetra Carapace": 3, "Flood Sac": 2, "Eltalite Ore": 3}},
	{"name": "True Leapfrog", "rank": "Master", "raw": 270, "affinity": 0, "defense": 20, "rarity": 8, "slots": [2, 13], "kinsect_level": 9, "element": ["Water", 20], "rampage_skills": [], "crafting_list": {"Zenny": 16000, "Jyuratodus Hardfang": 3, "Tetranadon Finedisc": 2, "Points": "MR Tetranadon 10 pts"}},
	{"name": "True Leapfrog +", "rank": "Master", "raw": 340, "affinity": 0, "defense": 30, "rarity": 10, "slots": [2, 13], "kinsect_level": 4, "element": ["Water", 22], "rampage_skills": [], "crafting_list": {"Zenny": 60000, "Afflicted Blood": 7, "Points": "MR Tetranadon 30 pts"}},
	{"name": "Dauntless Bayonet", "rank": "Master", "raw": 260, "affinity": 0, "defense": 0, "rarity": 8, "slots": [1, 11], "kinsect_level": 8, "element": null, "rampage_skills": [], "crafting_list": {"Zenny": 18000, "Eltalite Ore": 5, "Frocium": 5, "Monster Essence": 4, "Ultimas Crystal": 1}},
	{"name": "Dauntless Bayonet +", "rank": "Master", "raw": 310, "affinity": 0, "defense": 0, "rarity": 8, "slots": [2, 11], "kinsect_level": 0, "element": null, "rampage_skills": [], "crafting_list": {"Zenny": 24000, "Centuria Ore": 2, "Meldspar Ore": 3, "Points": "MR Ore 12 pts"}},
	{"name": "Steel Dauntless Bayonet", "rank": "Master", "raw": 340, "affinity": 0, "defense": 0, "rarity": 10, "slots": [2, 11], "kinsect_level": 3, "element": null, "rampage_skills": [], "crafting_list": {"Zenny": 60000, "Afflicted Bone": 7, "Points": "MR Ore 20 pts"}},
	{"name": "Frostmoon Razorglaive", "rank": "Master", "raw": 300, "affinity": 0, "defense": 0, "rarity": 9, "slots": [1, 1, 12], "kinsect_level": 2, "element": ["Ice", 18], "rampage_skills": [], "crafting_list": {"Zenny": 36000, "Lunagaron Cortex": 3, "Frostbom Hardfang": 3, "Lunagaron Bluecore": 2, "Lunagaron Lash Shell": 2}},
	{"name": "Frostmoon Razorglaive +", "rank": "Master", "raw": 310, "affinity": 0, "defense": 0, "rarity": 9, "slots": [1, 1, 12], "kinsect_level": 3, "element": ["Ice", 20], "rampage_skills": [], "crafting_list": {"Zenny": 52000, "Malzeno Tail": 2, "Lunagaron Frost Jewel": 1, "Points": "MR Lunagaron 10 pts"}},
	{"name": "Iceberg Tunggul", "rank": "Master", "raw": 330, "affinity": 0, "defense": 0, "rarity": 10, "slots": [1, 1, 12], "kinsect_level": 4, "element": ["Ice", 23], "rampage_skills": [], "crafting_list": {"Zenny": 60000, "Afflicted Claw": 5, "Afflicted Shell": 5, "Points": "MR Lunagaron 30 pts"}},
	{"name": "Thunder Tusk", "rank": "Master", "raw": 300, "affinity": 20, "defense": 0, "rarity": 9, "slots": [1, 12], "kinsect_level": 2, "element": ["Thunder", 21], "rampage_skills": [], "crafting_list": {"Zenny": 36000, "Astalos Scissortailblade": 2, "Astalos Wingripper": 2, "Heavy Astalos Shell": 4, "Sapphiron Ore": 2}},
	{"name": "Thunder Tusk +", "rank": "Master", "raw": 310, "affinity": 20, "defense": 0, "rarity": 9, "slots": [1, 12], "kinsect_level": 3, "element": ["Thunder", 23], "rampage_skills": [], "crafting_list": {"Zenny": 52000, "Fire Dragon Hardclaw": 2, "Astalos Mantle": 1, "Points": "MR Astalos 10 pts"}},
	{"name": "Thunder Dragon", "rank": "Master", "raw": 320, "affinity": 20, "defense": 0, "rarity": 10, "slots": [1, 12], "kinsect_level": 4, "element": ["Thunder", 25], "rampage_skills": [], "crafting_list": {"Zenny": 60000, "Afflicted Claw": 1, "Afflicted Scale": 1, "Astalos Mantle": 1, "Points": "MR Astalos 30 pts"}},
	{"name": "Firedance Rathmaul +", "rank": "Master", "raw": 310, "affinity": 0, "defense": 0, "rarity": 9, "slots": [1, 13], "kinsect_level": 2, "element": ["Fire", 44], "rampage_skills": [], "crafting_list": {"Zenny": 54000, "Rathalos Shard": 6, "Rathalos Lash": 3, "Conflagrant Sac": 3, "Rathalos Mantle": 1}},
	{"name": "Fiery Rath", "rank": "Master", "raw": 320, "affinity": 0, "defense": 0, "rarity": 10, "slots": [2, 13], "kinsect_level": 4, "element": ["Fire", 50], "rampage_skills": [], "crafting_list": {"Zenny": 60000, "Afflicted Claw": 5, "Afflicted Scale": 5, "Points": "MR Rathalos 30 pts"}},
	{"name": "Full Bolt Chamber +", "rank": "Master", "raw": 260, "affinity": 0, "defense": 0, "rarity": 8, "slots": [2, 1, 13], "kinsect_level": 9, "element": ["Thunder", 40], "rampage_skills": [], "crafting_list": {"Zenny": 16000, "Pearl Glosshide": 3, "Mystic Hardfang": 2, "Lightning Sac": 2}},
	{"name": "Surge Chamber", "rank": "Master", "raw": 290, "affinity": 0, "defense": 0, "rarity": 8, "slots": [2, 1, 13], "kinsect_level": 1, "element": ["Thunder", 42], "rampage_skills": [], "crafting_list": {"Zenny": 24000, "Rakna-Kadaki Silk +": 2, "Khezu Special Cut": 1, "Points": "MR Khezu 8 pts"}},
	{"name": "Surge Chamber +", "rank": "Master", "raw": 320, "affinity": 0, "defense": 0, "rarity": 10, "slots": [3, 1, 13], "kinsect_level": 3, "element": ["Thunder", 48], "rampage_skills": [], "crafting_list": {"Zenny": 60000, "Afflicted Blood": 7, "Points": "MR Khezu 30 pts"}},
	{"name": "Queen Regalia +", "rank": "Master", "raw": 270, "affinity": 0, "defense": 0, "rarity": 8, "slots": [1, 11], "kinsect_level": 9, "element": ["Poison", 26], "rampage_skills": [], "crafting_list": {"Zenny": 24000, "Rathian Surspike": 4, "Rathian Cortex": 5, "Deadly Poison Sac": 3, "Ultimas Crystal": 1}},
	{"name": "Empress Regalia", "rank": "Master", "raw": 310, "affinity": 0, "defense": 0, "rarity": 9, "slots": [1, 11], "kinsect_level": 1, "element": ["Poison", 28], "rampage_skills": [], "crafting_list": {"Zenny": 36000, "Rathalos Cortex": 2, "Rathian Mantle": 1, "Points": "MR Rathian 12 pts"}},
	{"name": "Empress Regalia +", "rank": "Master", "raw": 340, "affinity": 0, "defense": 0, "rarity": 10, "slots": [2, 11], "kinsect_level": 5, "element": ["Poison", 29], "rampage_skills": [], "crafting_list": {"Zenny": 60000, "Afflicted Scale": 7, "Points": "MR Rathian 30 pts"}},
	{"name": "Rosenstange", "rank": "Master", "raw": 300, "affinity": 20, "defense": 0, "rarity": 9, "slots": [1, 12], "kinsect_level": 1, "element": ["Fire", 14], "rampage_skills": [], "crafting_list": {"Zenny": 36000, "Espinas Hardhorn": 1, "Espinas Surspike": 2, "Espinas Lash": 1, "Espinas Cortex": 2}},
	{"name": "Rosenstange +", "rank": "Master", "raw": 310, "affinity": 20, "defense": 0, "rarity": 9, "slots": [1, 12], "kinsect_level": 3, "element": ["Fire", 16], "rampage_skills": [], "crafting_list": {"Zenny": 52000, "Chameleos Lash": 1, "Espinas Mantle": 1, "Points": "MR Espinas 12 pts"}},
	{"name": "Rosenspringen", "rank": "Master", "raw": 320, "affinity": 20, "defense": 0, "rarity": 10, "slots": [1, 12], "kinsect_level": 4, "element": ["Fire", 21], "rampage_skills": [], "crafting_list": {"Zenny": 60000, "Afflicted Fang": 5, "Afflicted Scale": 5, "Points": "MR Espinas 30 pts"}},
	{"name": "Dawnmoon Glaive", "rank": "Master", "raw": 240, "affinity": 0, "defense": 0, "rarity": 8, "slots": [2, 13], "kinsect_level": 8, "element": ["Fire", 31], "rampage_skills": [], "crafting_list": {"Zenny": 12000, "Aknosom Head-Crest": 2, "Aknosom Plume": 4, "Eltalite Ore": 3}},
	{"name": "Dawnmoon Glaive +", "rank": "Master", "raw": 260, "affinity": 0, "defense": 0, "rarity": 8, "slots": [2, 13], "kinsect_level": 9, "element": ["Fire", 35], "rampage_skills": [], "crafting_list": {"Zenny": 16000, "Orangaten Talon": 2, "Aknosom Burnbeak": 1, "Fey Wyvern Gem": 1}},
	{"name": "Dawnmoon Beambreak", "rank": "Master", "raw": 330, "affinity": 0, "defense": 0, "rarity": 10, "slots": [3, 13], "kinsect_level": 3, "element": ["Fire", 43], "rampage_skills": [], "crafting_list": {"Zenny": 60000, "Afflicted Monster Bone": 7, "Points": "MR Aknosom 30 pts"}},
	{"name": "Kulu Pike +", "rank": "Master", "raw": 250, "affinity": 15, "defense": 0, "rarity": 8, "slots": [1, 1, 1, 11], "kinsect_level": 8, "element": null, "rampage_skills": [], "crafting_list": {"Zenny": 12000, "Kulu-Ya-Ku Shard": 4, "Kulu-Ya-Ku Thickhide": 2, "Colossal Drill Beak": 2, "Twisted Stiffbone": 1}},
	{"name": "Kulu Katolos Pike", "rank": "Master", "raw": 330, "affinity": 15, "defense": 0, "rarity": 10, "slots": [1, 1, 1, 11], "kinsect_level": 3, "element": null, "rampage_skills": [], "crafting_list": {"Zenny": 60000, "Afflicted Pelt": 7, "Points": "MR Kulu-Ya-Ku 20 pts"}},
	{"name": "Shocking Pike +", "rank": "Master", "raw": 250, "affinity": 10, "defense": 0, "rarity": 8, "slots": [1, 12], "kinsect_level": 9, "element": ["Thunder", 28], "rampage_skills": [], "crafting_list": {"Zenny": 16000, "Tobi-Kadachi Thickfur": 4, "Tobi-Kadachi Hardclaw": 2, "Tobi-Kadachi Cathode": 2}},
	{"name": "Thundering Pike", "rank": "Master", "raw": 280, "affinity": 10, "defense": 0, "rarity": 8, "slots": [2, 12], "kinsect_level": 1, "element": ["Thunder", 30], "rampage_skills": [], "crafting_list": {"Zenny": 24000, "Monster Slogbone": 2, "Tobi-Kadachi Cathode": 2, "Large Wyvern Gem": 1, "Points": "MR Tobi-Kadachi 10 pts"}},
	{"name": "Thundering Pike +", "rank": "Master", "raw": 330, "affinity": 10, "defense": 0, "rarity": 10, "slots": [2, 2, 12], "kinsect_level": 4, "element": ["Thunder", 32], "rampage_skills": [], "crafting_list": {"Zenny": 60000, "Afflicted Scale": 7, "Points": "MR Tobi-Kadachi 30 pts"}},
	{"name": "Lagombavarice +", "rank": "Master", "raw": 240, "affinity": 0, "defense": 0, "rarity": 8, "slots": [1, 1, 13], "kinsect_level": 8, "element": ["Ice", 33], "rampage_skills": [], "crafting_list": {"Zenny": 12000, "Lagombi Cuirass": 2, "Lagombi Fur": 3, "Frocium": 1}},
	{"name": "Sawtooth", "rank": "Master", "raw": 330, "affinity": 0, "defense": 0, "rarity": 10, "slots": [2, 1, 13], "kinsect_level": 3, "element": ["Ice", 44], "rampage_skills": [], "crafting_list": {"Zenny": 60000, "Afflicted Bone": 7, "Points": "MR Lagombi 20 pts"}},
	{"name": "Sturdy Glaive Redux +", "rank": "Master", "raw": 270, "affinity": 0, "defense": 0, "rarity": 8, "slots": [13], "kinsect_level": 9, "element": null, "rampage_skills": [], "crafting_list": {"Zenny": 18000, "Twisted Stiffbone": 6, "Monster Essence": 3, "Eltalite Ore": 3, "Dragonbone Artifact": 1}},
	{"name": "Stalwart Glaive", "rank": "Master", "raw": 320, "affinity": 0, "defense": 0, "rarity": 8, "slots": [13], "kinsect_level": 0, "element": null, "rampage_skills": [], "crafting_list": {"Zenny": 24000, "Monster Slogbone": 3, "Boggi Shard": 3, "Almudron Shard": 3, "Points": "MR Bone 10 pts"}},
	{"name": "Stalwart Glaive +", "rank": "Master", "raw": 350, "affinity": 0, "defense": 0, "rarity": 10, "slots": [13], "kinsect_level": 4, "element": null, "rampage_skills": [], "crafting_list": {"Zenny": 60000, "Afflicted Bone": 7, "Blackened Stiffbone": 5, "Points": "MR Bone 20 pts"}},
	{"name": "Altair", "rank": "Master", "raw": 310, "affinity": 10, "defense": 0, "rarity": 9, "slots": [1, 12], "kinsect_level": 2, "element": null, "rampage_skills": [], "crafting_list": {"Zenny": 36000, "Points": "Seregios lmpaler+ x2"}},
	{"name": "Altair +", "rank": "Master", "raw": 320, "affinity": 10, "defense": 0, "rarity": 9, "slots": [1, 12], "kinsect_level": 3, "element": null, "rampage_skills": [], "crafting_list": {"Zenny": 52000, "Pure Dragon Blood": 3, "Seregios Lens": 1, "Points": "MR Seregios 15 pts"}},
	{"name": "Alteal", "rank": "Master", "raw": 330, "affinity": 10, "defense": 0, "rarity": 10, "slots": [1, 12], "kinsect_level": 3, "element": null, "rampage_skills": [], "crafting_list": {"Zenny": 60000, "Afflicted Fang": 5, "Afflicted Scale": 5, "Points": "MR Seregios 30 pts"}},
	{"name": "Shell Intoner", "rank": "Master", "raw": 250, "affinity": 0, "defense": 30, "rarity": 8, "slots": [3, 13], "kinsect_level": 9, "element": ["Water", 18], "rampage_skills": [], "crafting_list": {"Zenny": 52000, "Hermitaur Hardclaw": 5, "Tiny Hermitaur Shell": 3, "Timewom Crimson Horn": 1, "Dragonbone Artifact": 1}},
	{"name": "Shell Intoner +", "rank": "Master", "raw": 300, "affinity": 0, "defense": 30, "rarity": 8, "slots": [3, 13], "kinsect_level": 1, "element": ["Water", 22], "rampage_skills": [], "crafting_list": {"Zenny": 24000, "Rakna-Kadaki Hardclaw": 2, "Timewom Crimson Horn": 1, "Points": "MR Daimyo Hermitaur 10 pts"}},
	{"name": "Crab lntoner", "rank": "Master", "raw": 330, "affinity": 0, "defense": 30, "rarity": 10, "slots": [13], "kinsect_level": 5, "element": ["Water", 27], "rampage_skills": [], "crafting_list": {"Zenny": 60000, "Afflicted Blood": 7, "Points": "MR Daimyo Hermitaur 30 pts"}},
	{"name": "Highest of Glaives +", "rank": "Master", "raw": 240, "affinity": 0, "defense": 0, "rarity": 8, "slots": [3, 12], "kinsect_level": 8, "element": ["Paralysis", 26], "rampage_skills": [], "crafting_list": {"Zenny": 12000, "Volvidon Talon": 2, "Crushing Fang": 2, "Vespoid Razorwing": 4}},
	{"name": "Stratosphere Glaive", "rank": "Master", "raw": 290, "affinity": 0, "defense": 0, "rarity": 8, "slots": [3, 12], "kinsect_level": 9, "element": ["Paralysis", 27], "rampage_skills": [], "crafting_list": {"Zenny": 24000, "Ceanataur Shell": 2, "Ultraplegia Sac": 2, "Points": "MR Small Monster 8 pts"}},
	{"name": "Stratosphere Glaive +", "rank": "Master", "raw": 330, "affinity": 0, "defense": 0, "rarity": 10, "slots": [3, 12], "kinsect_level": 3, "element": ["Paralysis", 30], "rampage_skills": [], "crafting_list": {"Zenny": 60000, "Afflicted Pelt": 7, "Overgrown Stiffbone": 5, "Points": "MR Small Monster 20 pts"}},
	{"name": "Tyrant Rod +", "rank": "Master", "raw": 340, "affinity": -10, "defense": 0, "rarity": 9, "slots": [12], "kinsect_level": 1, "element": null, "rampage_skills": [], "crafting_list": {"Zenny": 36000, "Diablos Chine": 3, "Points": "Diablos Tailcase+ x2", "Monster Slogbone": 3}},
	{"name": "Horned Tyrant", "rank": "Master", "raw": 350, "affinity": -10, "defense": 0, "rarity": 9, "slots": [12], "kinsect_level": 2, "element": null, "rampage_skills": [], "crafting_list": {"Zenny": 52000, "Large Elder Dragon Bone": 3, "Twisted Stouthorn": 2, "Large Wyvern Gem": 1, "Points": "MR Diablos 12 pts"}},
	{"name": "Horned Tyrant +", "rank": "Master", "raw": 360, "affinity": -10, "defense": 0, "rarity": 10, "slots": [12], "kinsect_level": 3, "element": null, "rampage_skills": [], "crafting_list": {"Zenny": 60000, "Afflicted Fang": 5, "Afflicted Shell": 5, "Points": "MR Diablos 30 pts"}},
	{"name": "Gnashing Flammenkaefer +", "rank": "Master", "raw": 280, "affinity": -15, "defense": 0, "rarity": 8, "slots": [2, 1, 12], "kinsect_level": 9, "element": ["Fire", 23], "rampage_skills": [], "crafting_list": {"Zenny": 16000, "Anjanath Hardfang": 4, "Anjanath Fur": 3, "Monster Toughbone": 3}},
	{"name": "Lohenspire", "rank": "Master", "raw": 330, "affinity": -15, "defense": 0, "rarity": 9, "slots": [2, 1, 12], "kinsect_level": 2, "element": ["Fire", 25], "rampage_skills": [], "crafting_list": {"Zenny": 36000, "Tigrex Hardfang": 3, "Anjanath Mantle": 1}},
	{"name": "Lohenspire +", "rank": "Master", "raw": 350, "affinity": -15, "defense": 0, "rarity": 10, "slots": [2, 1, 12], "kinsect_level": 4, "element": ["Fire", 28], "rampage_skills": [], "crafting_list": {"Zenny": 60000, "Afflicted Scale": 7, "Points": "MR Anjanath 30 pts"}},
	{"name": "Abominable Snowpole", "rank": "Master", "raw": 310, "affinity": -20, "defense": 0, "rarity": 8, "slots": [3, 12], "kinsect_level": 1, "element": ["Ice", 18], "rampage_skills": [], "crafting_list": {"Zenny": 36000, "Goss Harag Allbrace": 5, "Goss Finehide": 8, "Dense Block of Ice": 5, "Dragonbone Artifact": 1}},
	{"name": "Abominable Snowpole +", "rank": "Master", "raw": 330, "affinity": -20, "defense": 0, "rarity": 9, "slots": [3, 12], "kinsect_level": 2, "element": ["Ice", 19], "rampage_skills": [], "crafting_list": {"Zenny": 36000, "Lunagaron Cortex": 2, "Goss Harag Bile +": 1, "Points": "MR Goss Harag 12 pts"}},
	{"name": "Far North Pole", "rank": "Master", "raw": 350, "affinity": -20, "defense": 0, "rarity": 10, "slots": [3, 12], "kinsect_level": 2, "element": ["Ice", 20], "rampage_skills": [], "crafting_list": {"None": 0, "Afflicted Claw": 7, "Points": "MR Goss Harag 30 pts"}},
	{"name": "Datura Pike +", "rank": "Master", "raw": 26, "affinity": 0, "defense": 0, "rarity": 8, "slots": [2, 1, 13], "kinsect_level": 9, "element": ["Poison", 31], "rampage_skills": [], "crafting_list": {"Zenny": 16000, "Pukei-Pukei Shard": 3, "Pukei-Pukei Fellwing": 2, "Large Pukei-Pukei Sac": 2}},
	{"name": "Datura Plume", "rank": "Master", "raw": 290, "affinity": 0, "defense": 0, "rarity": 8, "slots": [2, 1, 13], "kinsect_level": 0, "element": ["Poison", 33], "rampage_skills": [], "crafting_list": {"Zenny": 24000, "Nargacuga Blackfur+": 3, "Pukei-Pukei Lash": 2, "Fey Wyvern Gem": 1, "Points": "MR Pukei-Pukei 8 pts"}},
	{"name": "Datura Plume +", "rank": "Master", "raw": 330, "affinity": 0, "defense": 0, "rarity": 10, "slots": [2, 1, 13], "kinsect_level": 3, "element": ["Poison", 39], "rampage_skills": [], "crafting_list": {"Zenny": 60000, "Afflicted Scale": 7, "Points": "MR Pukei-Pukei 30 pts"}},
	{"name": "Midgard Storm", "rank": "Master", "raw": 280, "affinity": 15, "defense": 0, "rarity": 8, "slots": [1, 1, 1, 12], "kinsect_level": 0, "element": ["Ice", 30], "rampage_skills": [], "crafting_list": {"Zenny": 24000, "Amber Hardfang": 2, "Barioth Cortex": 3, "Barioth Lash": 2, "Cryo Sac": 3}},
	{"name": "Midgard Storm +", "rank": "Master", "raw": 300, "affinity": 15, "defense": 0, "rarity": 9, "slots": [1, 1, 1, 12], "kinsect_level": 2, "element": ["Ice", 32], "rampage_skills": [], "crafting_list": {"Zenny": 36000, "Tigrex Hardclaw": 2, "Barioth Thickfur": 2, "Large Wyvern Gem": 1, "Points": "MR Barioth 12 pts"}},
	{"name": "Pure Helltone", "rank": "Master", "raw": 320, "affinity": 15, "defense": 0, "rarity": 10, "slots": [1, 1, 1, 12], "kinsect_level": 4, "element": ["Ice", 33], "rampage_skills": [], "crafting_list": {"Zenny": 60000, "Afflicted Fang": 7, "Points": "MR Barioth 30 pts"}},
	{"name": "Bloom Royale +", "rank": "Master", "raw": 240, "affinity": 0, "defense": 0, "rarity": 8, "slots": [2, 1, 1, 13], "kinsect_level": 8, "element": ["Water", 34], "rampage_skills": [], "crafting_list": {"Zenny": 24000, "Almudron Hardclaw": 2, "Royal Ludroth Lash": 1, "Large Wyvern Gem": 1, "Points": "MR Ludroth 8 pts"}},
	{"name": "Waterspout Bloom", "rank": "Master", "raw": 290, "affinity": 0, "defense": 0, "rarity": 8, "slots": [2, 1, 1, 13], "kinsect_level": 0, "element": ["Water", 36], "rampage_skills": [], "crafting_list": {"Zenny": 24000, "Almudron Hardclaw": 2, "Royal Ludroth Lash": 1, "Large Wyvern Gem": 1, "Points": "MR Ludroth 8 pts"}},
	{"name": "Waterspout Bloom +", "rank": "Master", "raw": 330, "affinity": 0, "defense": 0, "rarity": 10, "slots": [2, 1, 1, 13], "kinsect_level": 3, "element": ["Water", 45], "rampage_skills": [], "crafting_list": {"Zenny": 60000, "Afflicted Monster Bone": 7, "Points": "MR Ludroth 30 pts"}},
	{"name": "Golm Glaive", "rank": "Master", "raw": 310, "affinity": 0, "defense": 0, "rarity": 8, "slots": [3, 1, 1, 13], "kinsect_level": 0, "element": null, "rampage_skills": [], "crafting_list": {"Zenny": 24000, "Garangolm Hardfang": 5, "Garangolm Fist": 2, "Golm Thick Juice": 1, "Golm Ploughtail": 2}},
	{"name": "Golm Glaive +", "rank": "Master", "raw": 330, "affinity": 0, "defense": 0, "rarity": 9, "slots": [3, 2, 1, 13], "kinsect_level": 1, "element": null, "rampage_skills": [], "crafting_list": {"Zenny": 36000, "Frostborn Hardfang": 1, "Large Beast Gem": 1, "Points": "MR Garangolm 10 pts"}},
	{"name": "Maneater", "rank": "Master", "raw": 360, "affinity": 0, "defense": 0, "rarity": 10, "slots": [2, 1, 13], "kinsect_level": 5, "element": null, "rampage_skills": [], "crafting_list": {"Zenny": 60000, "Afflicted Fang": 7, "Points": "MR Garangolm 30 pts"}},
	{"name": "Despot's Twinbolt +", "rank": "Master", "raw": 310, "affinity": 0, "defense": 0, "rarity": 9, "slots": [1, 1, 12], "kinsect_level": 2, "element": ["Thunder", 30], "rampage_skills": [], "crafting_list": {"Zenny": 54000, "Zinogre Deathly Shocker": 6, "Zinogre Hardhorn": 3, "Zinogre Lash": 3, "Zinogre Skymerald": 1}},
	{"name": "Despot's Twindart", "rank": "Master", "raw": 310, "affinity": 0, "defense": 0, "rarity": 10, "slots": [1, 1, 12], "kinsect_level": 2, "element": ["Thunder", 39], "rampage_skills": [], "crafting_list": {"Zenny": 60000, "Afflicted Fang": 5, "Afflicted Shell": 5, "Points": "MR Zinogre 30 pts"}},
	{"name": "Hortadent Brada +", "rank": "Master", "raw": 240, "affinity": 0, "defense": 0, "rarity": 8, "slots": [2, 1, 1, 12], "kinsect_level": 9, "element": null, "rampage_skills": [], "crafting_list": {"Zenny": 12000, "Prized Stomach": 2, "Tough Claw": 3, "Monster Essence": 3}},
	{"name": "Altaroth Trident", "rank": "Master", "raw": 290, "affinity": 0, "defense": 0, "rarity": 8, "slots": [2, 1, 1, 12], "kinsect_level": 1, "element": null, "rampage_skills": [], "crafting_list": {"Zenny": 24000, "Rakna-Kadaki Hardclaw": 3, "Eroded Elder Skeleton": 2, "Points": "MR Neopteron 8 pts"}},
	{"name": "Altaroth Trident +", "rank": "Master", "raw": 330, "affinity": 0, "defense": 0, "rarity": 10, "slots": [3, 2, 1, 12], "kinsect_level": 5, "element": null, "rampage_skills": [], "crafting_list": {"Zenny": 60000, "Afflicted Bone": 7, "Points": "MR Neopteron 20 pts"}},
	{"name": "Rielle Du Red", "rank": "Master", "raw": 240, "affinity": 0, "defense": 0, "rarity": 8, "slots": [3, 1, 12], "kinsect_level": 8, "element": ["Fire", 27], "rampage_skills": [], "crafting_list": {"Zenny": 16000, "Purecrystal": 2, "Aknosom Head-Crest": 2, "Conflagrant Sac": 2, "Points": "MR Neopteron 12 pts"}},
	{"name": "Rielle Tre Red", "rank": "Master", "raw": 280, "affinity": 0, "defense": 0, "rarity": 8, "slots": [3, 1, 12], "kinsect_level": 1, "element": ["Fire", 30], "rampage_skills": [], "crafting_list": {"Zenny": 24000, "Points": "MR Neopteron 12 pts", "Monster Essence": 4}},
	{"name": "Rielle Kvar Red", "rank": "Master", "raw": 330, "affinity": 0, "defense": 0, "rarity": 10, "slots": [1, 1, 12], "kinsect_level": 5, "element": ["Fire", 32], "rampage_skills": [], "crafting_list": {"Zenny": 60000, "Afflicted Monster Bone": 7, "Points": "MR Neopteron 20 pts"}},
	{"name": "Rielle Du Black", "rank": "Master", "raw": 280, "affinity": 0, "defense": 0, "rarity": 8, "slots": [3, 1, 12], "kinsect_level": 1, "element": ["Dragon", 31], "rampage_skills": [], "crafting_list": {"Zenny": 24000, "Rakna-Kadaki Cortex": 3, "Prized Stomach": 2, "Points": "MR Neopteron 12 pts"}},
	{"name": "Rielle Tre Black", "rank": "Master", "raw": 330, "affinity": 0, "defense": 0, "rarity": 10, "slots": [1, 1, 12], "kinsect_level": 5, "element": ["Dragon", 33], "rampage_skills": [], "crafting_list": {"Zenny": 60000, "Afflicted Shell": 7, "Points": "MR Neopteron 20 pts"}},
	{"name": "Rielle Du White", "rank": "Master", "raw": 250, "affinity": 0, "defense": 0, "rarity": 8, "slots": [3, 1, 12], "kinsect_level": 9, "element": ["Ice", 26], "rampage_skills": [], "crafting_list": {"Zenny": 16000, "Purecrystal": 2, "Lagombi Frigidclaw": 3, "Points": "MR Neopteron 12 pts"}},
	{"name": "Rielle Tre White", "rank": "Master", "raw": 330, "affinity": 0, "defense": 0, "rarity": 10, "slots": [1, 1, 12], "kinsect_level": 5, "element": ["Ice", 31], "rampage_skills": [], "crafting_list": {"Zenny": 60000, "Afflicted Monster Bone": 7, "Points": "MR Neopteron 20 pts"}},
	{"name": "Rielle Du Green", "rank": "Master", "raw": 260, "affinity": 0, "defense": 0, "rarity": 8, "slots": [1, 1, 1, 11], "kinsect_level": 9, "element": ["Paralysis", 21], "rampage_skills": [], "crafting_list": {"Zenny": 16000, "Purecrystal": 2, "Ultraplegia Sac": 2, "Points": "MR Neopteron 12 pts"}},
	{"name": "Rielle Tre Green", "rank": "Master", "raw": 320, "affinity": 0, "defense": 0, "rarity": 10, "slots": [1, 1, 1, 11], "kinsect_level": 4, "element": ["Paralysis", 22], "rampage_skills": [], "crafting_list": {"Zenny": 60000, "Afflicted Monster Bone": 7, "Points": "MR Neopteron 20 pts"}},
	{"name": "Sinister Shadowstaff +", "rank": "Master", "raw": 290, "affinity": 0, "defense": 0, "rarity": 8, "slots": [2, 1, 12], "kinsect_level": 0, "element": ["Blast", 24], "rampage_skills": [], "crafting_list": {"Zenny": 24000, "Magna Ascended Blade": 2, "Magnamalo Cortex": 3, "Magnamalo Bladeshell": 2, "Points": "Magnamalo Soulprism+ x2"}},
	{"name": "Mighty Soulromancer", "rank": "Master", "raw": 320, "affinity": 0, "defense": 0, "rarity": 9, "slots": [2, 1, 12], "kinsect_level": 3, "element": ["Blast", 26], "rampage_skills": [], "crafting_list": {"Zenny": 52000, "Conqueror's Seal": 2, "Magnamalo Speartail": 2, "Magnamalo Orb": 1, "Points": "MR Magnamalo 10 pts"}},
	{"name": "Leumundslist", "rank": "Master", "raw": 290, "affinity": 20, "defense": 0, "rarity": 9, "slots": [1, 12], "kinsect_level": 2, "element": ["Dragon", 20], "rampage_skills": [], "crafting_list": {"Zenny": 39000, "Gore Magala Cortex": 5, "Gore Magala Sensor": 1, "Monster Essence": 2, "Ultimas Crystal ": 1}},
	{"name": "Leumundslist +", "rank": "Master", "raw": 310, "affinity": 20, "defense": 0, "rarity": 9, "slots": [2, 12], "kinsect_level": 3, "element": ["Dragon", 25], "rampage_skills": [], "crafting_list": {"Zenny": 52000, "S. Magala Purifier": 3, "Gore Magala Mantle": 1, "Points": "MR Gore Magala 10 pts"}},
	{"name": "Leumundsbruch", "rank": "Master", "raw": 320, "affinity": 20, "defense": 0, "rarity": 10, "slots": [2, 12], "kinsect_level": 4, "element": ["Dragon", 30], "rampage_skills": [], "crafting_list": {"Zenny": 60000, "Afflicted Fang": 5, "Afflicted Shell": 5, "Points": "MR Gore Magala 30 pts"}},
	{"name": "Le Traqueur", "rank": "Master", "raw": 290, "affinity": 35, "defense": 0, "rarity": 9, "slots": [11], "kinsect_level": 4, "element": ["Dragon", 37], "rampage_skills": [], "crafting_list": {"Zenny": 52000, "S. Magala Purifier": 2, "S. Magala Hardhorn": 1, "S. Magala Cortex": 3, "Overgrown Stiffbone": 2}},
	{"name": "Le Miracle", "rank": "Master", "raw": 300, "affinity": 35, "defense": 0, "rarity": 10, "slots": [11], "kinsect_level": 4, "element": ["Dragon", 45], "rampage_skills": [], "crafting_list": {"Zenny": 60000, "Rajang Apoplexy": 2, "S. Magala Mantle": 1, "Points": "MR Shagaru Magala 10 pts"}},
	{"name": "Metalmangler +", "rank": "Master", "raw": 350, "affinity": -20, "defense": 0, "rarity": 9, "slots": [3, 12], "kinsect_level": 3, "element": ["Thunder", 26], "rampage_skills": [], "crafting_list": {"Zenny": 52000, "Rajang Wildpelt": 3, "Rajang Hardhorn": 1, "Rajang Hardfang": 3, "Solid Bone": 2}},
	{"name": "Metal Mutilator", "rank": "Master", "raw": 360, "affinity": -20, "defense": 0, "rarity": 10, "slots": [3, 12], "kinsect_level": 4, "element": ["Thunder", 27], "rampage_skills": [], "crafting_list": {"Zenny": 60000, "Horn of Origin +": 1, "Gold Rajang Pelt +": 2, "Points": "MR Rajang 15 pts"}},
	{"name": "Demonlord Cudgel", "rank": "Master", "raw": 330, "affinity": 0, "defense": 0, "rarity": 10, "slots": [2, 2, 11], "kinsect_level": 4, "element": ["Thunder", 16], "rampage_skills": [], "crafting_list": {"Zenny": 66000, "Gold Rajang Pelt +": 5, "Rajang Apoplexy": 2, "Ghoulish Gold Gorer": 3, " Rajang Heart": 1}},
	{"name": "Skysoar Hurricane", "rank": "Master", "raw": 340, "affinity": 0, "defense": 0, "rarity": 10, "slots": [12], "kinsect_level": 4, "element": ["Dragon", 19], "rampage_skills": [], "crafting_list": {"Zenny": 60000, "Ibushi Hardhorn": 1, "Ibushi Cortex": 2, "Points": "Ibushi Bluespike+ x2", "Wind Dragonsphire": 1}},
	{"name": "Skysoar Flash", "rank": "Master", "raw": 310, "affinity": 0, "defense": 0, "rarity": 10, "slots": [12], "kinsect_level": 5, "element": ["Thunder", 61], "rampage_skills": [], "crafting_list": {"Zenny": 60000, "Horn of Origin +": 1, "Narwa Tentacle +": 2, "Narwa Lighting Sac": 2, "Mantle of Origin": 1}},
	{"name": "Daora's Tethidine +", "rank": "Master", "raw": 310, "affinity": 0, "defense": 0, "rarity": 9, "slots": [1, 13], "kinsect_level": 2, "element": ["Ice", 46], "rampage_skills": [], "crafting_list": {"Zenny": 52000, "Daora Shard": 4, "Daora Hardhorn": 2, "Daora Lash": 2, "Large Elder Dragon Bone": 3}},
	{"name": "Daora's Samudra", "rank": "Master", "raw": 320, "affinity": 0, "defense": 0, "rarity": 10, "slots": [1, 13], "kinsect_level": 3, "element": ["Ice", 52], "rampage_skills": [], "crafting_list": {"Zenny": 60000, "Rouge Lancewing +": 1, "Daora Hardclaw": 3, "Large Elder Dragon Gem": 1, "Points": "MR Kushala 12 pts"}},
	{"name": "Hazy Caster +", "rank": "Master", "raw": 310, "affinity": 0, "defense": 0, "rarity": 9, "slots": [2, 1, 1, 12], "kinsect_level": 3, "element": ["Poison", 43], "rampage_skills": [], "crafting_list": {"Zenny": 52000, "Chameleos Finehide": 4, "Chameleos Hardhorn": 2, "Chameleos Lash": 2, "Pure Dragon Blood": 2}},
	{"name": "Veil Caster", "rank": "Master", "raw": 320, "affinity": 0, "defense": 0, "rarity": 10, "slots": [2, 2, 1, 12], "kinsect_level": 4, "element": ["Poison", 48], "rampage_skills": [], "crafting_list": {"Zenny": 60000, "Glittering Shell": 1, "Chameleos Fellwing": 3, "Large Elder Dragon Gem": 1, "Points": "MR Chameleos 12 pts"}},
	{"name": "Abyssal Insectoid", "rank": "Master", "raw": 350, "affinity": -25, "defense": 0, "rarity": 10, "slots": [13], "kinsect_level": 5, "element": ["Dragon", 12], "rampage_skills": [], "crafting_list": {"Zenny": 66000, "Archdemon Doomhorn": 2, "Abyssal Dragonscale": 4, "Archdemon Wingtalon": 2, "Abyssal Dragonsphire": 1}},
	{"name": "Crimson Springwing", "rank": "Master", "raw": 340, "affinity": 0, "defense": 0, "rarity": 10, "slots": [2, 12], "kinsect_level": 3, "element": ["Dragon", 50], "rampage_skills": [], "crafting_list": {"Zenny": 60000, "Rouge Lancewing +": 3, "Glittering Shell": 3, "Valstrax Helixtail": 2, "Red Dragonsphire": 1}},
	{"name": "Garamorse +", "rank": "Master", "raw": 260, "affinity": 0, "defense": 20, "rarity": 8, "slots": [2, 2, 13], "kinsect_level": 8, "element": ["Dragon", 32], "rampage_skills": [], "crafting_list": {"Zenny": 16000, "Sinister Gloomcloth": 3, "Dragonbone Artifact": 1, "Tough Claw": 3, "Rathian Surspike": 2}},
	{"name": "Darkmorse", "rank": "Master", "raw": 320, "affinity": 0, "defense": 20, "rarity": 10, "slots": [2, 2, 13], "kinsect_level": 3, "element": ["Dragon", 43], "rampage_skills": [], "crafting_list": {"Zenny": 60000, "Afflicted Blood": 7, "Anomaly Ticket": 1, "Points": "MR Monster 20 pts"}},
	{"name": "Magia Crescent +", "rank": "Master", "raw": 290, "affinity": 0, "defense": 5, "rarity": 8, "slots": [1, 1, 1, 13], "kinsect_level": 1, "element": ["Blast", 40], "rampage_skills": [], "crafting_list": {"Zenny": 24000, "Almud Ascetic Whisker": 2, "Monster Essence": 3, "Prairie Cricket": 3}},
	{"name": "Staff of Laertes", "rank": "Master", "raw": 320, "affinity": 0, "defense": 30, "rarity": 10, "slots": [2, 1, 1, 13], "kinsect_level": 5, "element": ["Blast", 46], "rampage_skills": [], "crafting_list": {"Zenny": 60000, "Afflicted Shell": 7, "Anomaly Ticket": 1, "Points": "MR Monster 20 pts"}},
	{"name": "New World Brush Glaive", "rank": "Master", "raw": 310, "affinity": -10, "defense": 0, "rarity": 8, "slots": [3, 12], "kinsect_level": 9, "element": ["Water", 13], "rampage_skills": [], "crafting_list": {"Zenny": 16000, "Goss Harag Frozen Fur": 2, "Flood Sac": 2, "Kamura Ticket": 2}},
	{"name": "Poet's Brush Glaive", "rank": "Master", "raw": 350, "affinity": -10, "defense": 0, "rarity": 10, "slots": [3, 12], "kinsect_level": 3, "element": ["Water", 14], "rampage_skills": [], "crafting_list": {"Zenny": 60000, "Afflicted Scale": 7, "Anomaly Ticket": 1, "Points": "MR Monster 20 pts"}},
	{"name": "Royal Order's Glaive", "rank": "Master", "raw": 290, "affinity": 10, "defense": 50, "rarity": 8, "slots": [2, 12], "kinsect_level": 0, "element": null, "rampage_skills": [], "crafting_list": {"Zenny": 27000, "Royal Order Certificate I": 1, "Eltalite Ore": 5, "Auroracanth Iceclaw": 2, "Sapphiron Ore": 3}},
	{"name": "Royal Order's Glaive +", "rank": "Master", "raw": 320, "affinity": 10, "defense": 50, "rarity": 10, "slots": [2, 1, 12], "kinsect_level": 4, "element": null, "rampage_skills": [], "crafting_list": {"Zenny": 60000, "Afflicted Fang": 5, "Afflicted Scale": 5, "Royal Order Certificate III": 4, "Points": "MR Monster 20 pts"}}
]